{
    "pageNumber": 1,
    "angle": 0.21628780663013458,
    "width": 8.2639,
    "height": 11.6667,
    "unit": "inch",
    "words": [
        {
            "content": "Formular",
            "polygon": [
                1.3533,
                1.2201,
                2.2635,
                1.2209,
                2.2633,
                1.4185,
                1.3528,
                1.4178
            ],
            "confidence": 0.996,
            "span": {
                "offset": 0,
                "length": 8
            }
        },
        {
            "content": "mit",
            "polygon": [
                2.3031,
                1.2208,
                2.6494,
                1.2197,
                2.6493,
                1.4185,
                2.3029,
                1.4185
            ],
            "confidence": 0.998,
            "span": {
                "offset": 9,
                "length": 3
            }
        },
        {
            "content": "Mitarbeiterinformationen",
            "polygon": [
                2.7153,
                1.2194,
                5.1921,
                1.2172,
                5.1921,
                1.4185,
                2.7153,
                1.4185
            ],
            "confidence": 0.992,
            "span": {
                "offset": 13,
                "length": 24
            }
        },
        {
            "content": "für",
            "polygon": [
                5.2679,
                1.2171,
                5.5516,
                1.2165,
                5.5518,
                1.4185,
                5.268,
                1.4185
            ],
            "confidence": 0.946,
            "span": {
                "offset": 38,
                "length": 3
            }
        },
        {
            "content": "den",
            "polygon": [
                5.6076,
                1.2165,
                5.9704,
                1.2166,
                5.9708,
                1.4185,
                5.6079,
                1.4185
            ],
            "confidence": 0.999,
            "span": {
                "offset": 42,
                "length": 3
            }
        },
        {
            "content": "Notfall",
            "polygon": [
                6.0528,
                1.2164,
                6.7194,
                1.2157,
                6.7194,
                1.4173,
                6.0532,
                1.4184
            ],
            "confidence": 0.995,
            "span": {
                "offset": 46,
                "length": 7
            }
        },
        {
            "content": "Zuletzt",
            "polygon": [
                1.3446,
                1.6098,
                1.7953,
                1.6108,
                1.7949,
                1.7546,
                1.3445,
                1.7544
            ],
            "confidence": 0.995,
            "span": {
                "offset": 54,
                "length": 7
            }
        },
        {
            "content": "aktualisiert:",
            "polygon": [
                1.8406,
                1.6105,
                2.5846,
                1.6108,
                2.5843,
                1.7546,
                1.8402,
                1.7546
            ],
            "confidence": 0.993,
            "span": {
                "offset": 62,
                "length": 13
            }
        },
        {
            "content": "21.10.2024",
            "polygon": [
                2.6132,
                1.611,
                3.3511,
                1.61,
                3.3511,
                1.7546,
                2.613,
                1.7546
            ],
            "confidence": 0.995,
            "span": {
                "offset": 76,
                "length": 10
            }
        },
        {
            "content": "Persönliche",
            "polygon": [
                1.3502,
                1.9572,
                2.3979,
                1.9591,
                2.3973,
                2.1313,
                1.35,
                2.1258
            ],
            "confidence": 0.977,
            "span": {
                "offset": 87,
                "length": 11
            }
        },
        {
            "content": "Informationen",
            "polygon": [
                2.465,
                1.9593,
                3.6988,
                1.9664,
                3.6988,
                2.1335,
                2.4643,
                2.1318
            ],
            "confidence": 0.994,
            "span": {
                "offset": 99,
                "length": 13
            }
        },
        {
            "content": "Mitarbeiternummer",
            "polygon": [
                2.1855,
                2.1712,
                3.4195,
                2.1754,
                3.4195,
                2.3166,
                2.1856,
                2.3095
            ],
            "confidence": 0.994,
            "span": {
                "offset": 113,
                "length": 17
            }
        },
        {
            "content": "96731",
            "polygon": [
                3.5286,
                2.1669,
                4.1718,
                2.1693,
                4.1718,
                2.347,
                3.5286,
                2.3454
            ],
            "confidence": 0.998,
            "span": {
                "offset": 131,
                "length": 5
            }
        },
        {
            "content": "Vorname",
            "polygon": [
                2.8073,
                2.3766,
                3.4252,
                2.38,
                3.4252,
                2.5099,
                2.8074,
                2.5085
            ],
            "confidence": 0.995,
            "span": {
                "offset": 137,
                "length": 7
            }
        },
        {
            "content": "Nina",
            "polygon": [
                3.5412,
                2.3859,
                4.0579,
                2.3903,
                4.0579,
                2.5521,
                3.5402,
                2.5472
            ],
            "confidence": 0.992,
            "span": {
                "offset": 145,
                "length": 4
            }
        },
        {
            "content": "Zweiter",
            "polygon": [
                2.2931,
                2.5694,
                2.7805,
                2.571,
                2.7803,
                2.7143,
                2.2931,
                2.7121
            ],
            "confidence": 0.994,
            "span": {
                "offset": 150,
                "length": 7
            }
        },
        {
            "content": "Vorname",
            "polygon": [
                2.8181,
                2.5714,
                3.4232,
                2.5715,
                3.4231,
                2.7173,
                2.818,
                2.7143
            ],
            "confidence": 0.999,
            "span": {
                "offset": 158,
                "length": 7
            }
        },
        {
            "content": "Luise",
            "polygon": [
                3.5215,
                2.5767,
                4.0522,
                2.5845,
                4.0522,
                2.748,
                3.5193,
                2.7438
            ],
            "confidence": 0.996,
            "span": {
                "offset": 166,
                "length": 5
            }
        },
        {
            "content": "Nachname",
            "polygon": [
                2.6995,
                2.7722,
                3.4195,
                2.7748,
                3.4195,
                2.911,
                2.6998,
                2.9085
            ],
            "confidence": 0.996,
            "span": {
                "offset": 172,
                "length": 8
            }
        },
        {
            "content": "Neumann",
            "polygon": [
                3.5543,
                2.7892,
                4.5024,
                2.7982,
                4.5024,
                2.9508,
                3.5528,
                2.9434
            ],
            "confidence": 0.926,
            "span": {
                "offset": 181,
                "length": 7
            }
        },
        {
            "content": "Rufname",
            "polygon": [
                2.8135,
                2.9704,
                3.4222,
                2.9746,
                3.4221,
                3.1097,
                2.8133,
                3.1087
            ],
            "confidence": 0.995,
            "span": {
                "offset": 189,
                "length": 7
            }
        },
        {
            "content": "Vini",
            "polygon": [
                3.5639,
                2.9944,
                4.018,
                2.9993,
                4.018,
                3.1502,
                3.5628,
                3.1453
            ],
            "confidence": 0.477,
            "span": {
                "offset": 197,
                "length": 4
            }
        },
        {
            "content": "Geschlecht",
            "polygon": [
                2.6776,
                3.1685,
                3.4252,
                3.1688,
                3.4252,
                3.3097,
                2.6775,
                3.3085
            ],
            "confidence": 0.994,
            "span": {
                "offset": 202,
                "length": 10
            }
        },
        {
            "content": "F",
            "polygon": [
                3.5502,
                3.1688,
                3.6874,
                3.1682,
                3.6874,
                3.3268,
                3.5491,
                3.3265
            ],
            "confidence": 0.996,
            "span": {
                "offset": 213,
                "length": 1
            }
        },
        {
            "content": "Nationalität",
            "polygon": [
                2.6729,
                3.3666,
                3.4252,
                3.367,
                3.4252,
                3.5067,
                2.6731,
                3.5048
            ],
            "confidence": 0.989,
            "span": {
                "offset": 215,
                "length": 12
            }
        },
        {
            "content": "Deutsch",
            "polygon": [
                3.5114,
                3.3506,
                4.2231,
                3.3504,
                4.2231,
                3.541,
                3.5114,
                3.532
            ],
            "confidence": 0.996,
            "span": {
                "offset": 228,
                "length": 7
            }
        },
        {
            "content": "Geburtsort",
            "polygon": [
                2.2555,
                3.5626,
                2.9466,
                3.5649,
                2.9463,
                3.7199,
                2.255,
                3.7129
            ],
            "confidence": 0.993,
            "span": {
                "offset": 236,
                "length": 10
            }
        },
        {
            "content": "(Land)",
            "polygon": [
                2.9898,
                3.5654,
                3.4138,
                3.5641,
                3.4138,
                3.7199,
                2.9895,
                3.7199
            ],
            "confidence": 0.992,
            "span": {
                "offset": 247,
                "length": 6
            }
        },
        {
            "content": "Bremen",
            "polygon": [
                3.5065,
                3.5561,
                4.2402,
                3.569,
                4.2402,
                3.7479,
                3.5041,
                3.7417
            ],
            "confidence": 0.992,
            "span": {
                "offset": 254,
                "length": 6
            }
        },
        {
            "content": "Anschrift",
            "polygon": [
                2.4349,
                3.766,
                3.0123,
                3.7658,
                3.012,
                3.9174,
                2.4346,
                3.9143
            ],
            "confidence": 0.994,
            "span": {
                "offset": 261,
                "length": 9
            }
        },
        {
            "content": "privat",
            "polygon": [
                3.0596,
                3.7665,
                3.4252,
                3.7661,
                3.4252,
                3.9188,
                3.0592,
                3.9169
            ],
            "confidence": 0.996,
            "span": {
                "offset": 271,
                "length": 6
            }
        },
        {
            "content": "Seestraße",
            "polygon": [
                3.5039,
                3.7591,
                4.5547,
                3.7575,
                4.555,
                3.9364,
                3.5023,
                3.9318
            ],
            "confidence": 0.982,
            "span": {
                "offset": 278,
                "length": 9
            }
        },
        {
            "content": "25",
            "polygon": [
                4.6185,
                3.7571,
                4.8614,
                3.7562,
                4.8614,
                3.9364,
                4.6187,
                3.9364
            ],
            "confidence": 0.998,
            "span": {
                "offset": 288,
                "length": 2
            }
        },
        {
            "content": "28195",
            "polygon": [
                3.5161,
                3.9584,
                4.0714,
                3.9611,
                4.0711,
                4.1357,
                3.5151,
                4.1311
            ],
            "confidence": 0.996,
            "span": {
                "offset": 291,
                "length": 5
            }
        },
        {
            "content": "Bremen",
            "polygon": [
                4.1337,
                3.9619,
                4.8785,
                3.9664,
                4.8785,
                4.135,
                4.1333,
                4.1357
            ],
            "confidence": 0.997,
            "span": {
                "offset": 297,
                "length": 6
            }
        },
        {
            "content": "Bundesland/Kanton",
            "polygon": [
                2.133,
                4.1596,
                3.4185,
                4.1612,
                3.4181,
                4.3091,
                2.1331,
                4.3043
            ],
            "confidence": 0.992,
            "span": {
                "offset": 304,
                "length": 17
            }
        },
        {
            "content": "Bremen",
            "polygon": [
                3.5363,
                4.1561,
                4.2687,
                4.1657,
                4.2687,
                4.3408,
                3.5344,
                4.3363
            ],
            "confidence": 0.992,
            "span": {
                "offset": 322,
                "length": 6
            }
        },
        {
            "content": "Telefon",
            "polygon": [
                2.5223,
                4.3598,
                3.0041,
                4.3608,
                3.0039,
                4.5126,
                2.5226,
                4.5096
            ],
            "confidence": 0.995,
            "span": {
                "offset": 329,
                "length": 7
            }
        },
        {
            "content": "privat",
            "polygon": [
                3.0565,
                4.3615,
                3.4195,
                4.3616,
                3.4195,
                4.5156,
                3.0563,
                4.5127
            ],
            "confidence": 0.995,
            "span": {
                "offset": 337,
                "length": 6
            }
        },
        {
            "content": "+494211230987",
            "polygon": [
                3.503,
                4.3576,
                5.1521,
                4.3476,
                5.1521,
                4.5275,
                3.5023,
                4.526
            ],
            "confidence": 0.988,
            "span": {
                "offset": 344,
                "length": 13
            }
        },
        {
            "content": "Handy",
            "polygon": [
                2.9782,
                4.5562,
                3.4138,
                4.5604,
                3.4138,
                4.7139,
                2.9773,
                4.7097
            ],
            "confidence": 0.998,
            "span": {
                "offset": 358,
                "length": 5
            }
        },
        {
            "content": "+",
            "polygon": [
                3.5127,
                4.552,
                3.5938,
                4.5521,
                3.5932,
                4.725,
                3.5119,
                4.7239
            ],
            "confidence": 0.984,
            "span": {
                "offset": 364,
                "length": 1
            }
        },
        {
            "content": "491711230987",
            "polygon": [
                3.6286,
                4.5521,
                5.1521,
                4.5483,
                5.1521,
                4.7282,
                3.6281,
                4.7255
            ],
            "confidence": 0.992,
            "span": {
                "offset": 366,
                "length": 12
            }
        },
        {
            "content": "Fax",
            "polygon": [
                2.7595,
                4.7591,
                3.01,
                4.7609,
                3.0095,
                4.9134,
                2.759,
                4.9106
            ],
            "confidence": 0.999,
            "span": {
                "offset": 379,
                "length": 3
            }
        },
        {
            "content": "privat",
            "polygon": [
                3.0576,
                4.7614,
                3.4195,
                4.7612,
                3.4195,
                4.9142,
                3.0571,
                4.9131
            ],
            "confidence": 0.995,
            "span": {
                "offset": 383,
                "length": 6
            }
        },
        {
            "content": "+49",
            "polygon": [
                3.5259,
                4.7469,
                3.8651,
                4.7454,
                3.8648,
                4.9271,
                3.5253,
                4.9271
            ],
            "confidence": 0.992,
            "span": {
                "offset": 390,
                "length": 3
            }
        },
        {
            "content": "4211",
            "polygon": [
                3.9535,
                4.7448,
                4.3871,
                4.7479,
                4.387,
                4.9268,
                3.9533,
                4.9264
            ],
            "confidence": 0.984,
            "span": {
                "offset": 394,
                "length": 4
            }
        },
        {
            "content": "230988",
            "polygon": [
                4.4638,
                4.748,
                5.1407,
                4.7497,
                5.1407,
                4.9276,
                4.4637,
                4.9266
            ],
            "confidence": 0.995,
            "span": {
                "offset": 399,
                "length": 6
            }
        },
        {
            "content": "E-Mail-Adresse",
            "polygon": [
                2.0087,
                4.955,
                3.006,
                4.9596,
                3.0052,
                5.1116,
                2.0084,
                5.1048
            ],
            "confidence": 0.992,
            "span": {
                "offset": 406,
                "length": 14
            }
        },
        {
            "content": "privat",
            "polygon": [
                3.0584,
                4.96,
                3.4195,
                4.9597,
                3.4195,
                5.1126,
                3.0575,
                5.1113
            ],
            "confidence": 0.995,
            "span": {
                "offset": 421,
                "length": 6
            }
        },
        {
            "content": "nina.neumann@example.com",
            "polygon": [
                3.5454,
                4.974,
                6.537,
                4.971,
                6.537,
                5.1497,
                3.5453,
                5.1453
            ],
            "confidence": 0.891,
            "span": {
                "offset": 428,
                "length": 24
            }
        },
        {
            "content": "Geburtstag",
            "polygon": [
                1.7502,
                5.1539,
                2.466,
                5.1545,
                2.4655,
                5.3144,
                1.7496,
                5.3077
            ],
            "confidence": 0.994,
            "span": {
                "offset": 453,
                "length": 10
            }
        },
        {
            "content": "(TT/MM/JJJJ)",
            "polygon": [
                2.5156,
                5.1546,
                3.4081,
                5.1562,
                3.4081,
                5.3149,
                2.5151,
                5.3148
            ],
            "confidence": 0.962,
            "span": {
                "offset": 464,
                "length": 12
            }
        },
        {
            "content": "1996-01-05",
            "polygon": [
                3.5246,
                5.1679,
                4.8159,
                5.1673,
                4.8159,
                5.332,
                3.5233,
                5.3287
            ],
            "confidence": 0.994,
            "span": {
                "offset": 477,
                "length": 10
            }
        },
        {
            "content": "Sozialversicherungsnummer",
            "polygon": [
                1.5606,
                5.3528,
                3.4138,
                5.3622,
                3.4138,
                5.5139,
                1.5601,
                5.5027
            ],
            "confidence": 0.992,
            "span": {
                "offset": 488,
                "length": 25
            }
        },
        {
            "content": "567890123",
            "polygon": [
                3.5202,
                5.3551,
                4.5993,
                5.3612,
                4.5993,
                5.5291,
                3.5186,
                5.523
            ],
            "confidence": 0.996,
            "span": {
                "offset": 514,
                "length": 9
            }
        },
        {
            "content": "Ausweisnummer",
            "polygon": [
                2.3163,
                5.5573,
                3.4195,
                5.5602,
                3.4195,
                5.7014,
                2.3157,
                5.6986
            ],
            "confidence": 0.995,
            "span": {
                "offset": 524,
                "length": 13
            }
        },
        {
            "content": "356789012",
            "polygon": [
                3.4951,
                5.5537,
                4.5537,
                5.5576,
                4.5537,
                5.7226,
                3.4943,
                5.7228
            ],
            "confidence": 0.615,
            "span": {
                "offset": 538,
                "length": 9
            }
        },
        {
            "content": "Führerscheinnummer",
            "polygon": [
                2.0171,
                5.754,
                3.4138,
                5.7599,
                3.4138,
                5.9017,
                2.0164,
                5.8968
            ],
            "confidence": 0.992,
            "span": {
                "offset": 548,
                "length": 18
            }
        },
        {
            "content": "M56789012",
            "polygon": [
                3.5015,
                5.7529,
                4.7532,
                5.7535,
                4.7532,
                5.9226,
                3.5009,
                5.92
            ],
            "confidence": 0.979,
            "span": {
                "offset": 567,
                "length": 9
            }
        },
        {
            "content": "Medizinische",
            "polygon": [
                1.3402,
                5.9567,
                2.4926,
                5.962,
                2.4918,
                6.1348,
                1.34,
                6.1312
            ],
            "confidence": 0.996,
            "span": {
                "offset": 577,
                "length": 12
            }
        },
        {
            "content": "Informationen",
            "polygon": [
                2.5576,
                5.9621,
                3.79,
                5.9663,
                3.79,
                6.135,
                2.5569,
                6.1347
            ],
            "confidence": 0.993,
            "span": {
                "offset": 590,
                "length": 13
            }
        },
        {
            "content": "Name",
            "polygon": [
                2.2799,
                6.1718,
                2.6716,
                6.1724,
                2.6712,
                6.3176,
                2.2797,
                6.3178
            ],
            "confidence": 0.992,
            "span": {
                "offset": 604,
                "length": 4
            }
        },
        {
            "content": "des",
            "polygon": [
                2.717,
                6.1725,
                2.9463,
                6.174,
                2.9453,
                6.3192,
                2.7165,
                6.3178
            ],
            "confidence": 0.996,
            "span": {
                "offset": 609,
                "length": 3
            }
        },
        {
            "content": "Arztes",
            "polygon": [
                2.9869,
                6.1743,
                3.4138,
                6.1747,
                3.4138,
                6.3205,
                2.986,
                6.3192
            ],
            "confidence": 0.997,
            "span": {
                "offset": 613,
                "length": 6
            }
        },
        {
            "content": "Dr.",
            "polygon": [
                3.5573,
                6.155,
                3.9225,
                6.1545,
                3.9217,
                6.3518,
                3.5559,
                6.3486
            ],
            "confidence": 0.997,
            "span": {
                "offset": 620,
                "length": 3
            }
        },
        {
            "content": "Martin",
            "polygon": [
                3.993,
                6.1554,
                4.653,
                6.1577,
                4.6526,
                6.355,
                3.9923,
                6.3514
            ],
            "confidence": 0.995,
            "span": {
                "offset": 624,
                "length": 6
            }
        },
        {
            "content": "Weiss",
            "polygon": [
                4.7139,
                6.1579,
                5.3117,
                6.1622,
                5.3117,
                6.3535,
                4.7136,
                6.3555
            ],
            "confidence": 0.997,
            "span": {
                "offset": 631,
                "length": 5
            }
        },
        {
            "content": "Adresse",
            "polygon": [
                2.857,
                6.3769,
                3.4138,
                6.3804,
                3.4138,
                6.5151,
                2.8565,
                6.5133
            ],
            "confidence": 0.995,
            "span": {
                "offset": 637,
                "length": 7
            }
        },
        {
            "content": "Altstadt",
            "polygon": [
                3.5319,
                6.3732,
                4.3986,
                6.3684,
                4.3981,
                6.5496,
                3.5311,
                6.5495
            ],
            "confidence": 0.993,
            "span": {
                "offset": 645,
                "length": 8
            }
        },
        {
            "content": "1",
            "polygon": [
                4.4489,
                6.3677,
                4.605,
                6.3694,
                4.605,
                6.5486,
                4.4483,
                6.5486
            ],
            "confidence": 0.99,
            "span": {
                "offset": 654,
                "length": 1
            }
        },
        {
            "content": "28195",
            "polygon": [
                3.5174,
                6.5609,
                4.1118,
                6.5658,
                4.1113,
                6.7497,
                3.5164,
                6.743
            ],
            "confidence": 0.988,
            "span": {
                "offset": 656,
                "length": 5
            }
        },
        {
            "content": "Bremen",
            "polygon": [
                4.1958,
                6.5675,
                4.9355,
                6.5721,
                4.9355,
                6.7513,
                4.1953,
                6.7509
            ],
            "confidence": 0.995,
            "span": {
                "offset": 662,
                "length": 6
            }
        },
        {
            "content": "Rufnummer",
            "polygon": [
                2.639,
                6.77,
                3.4138,
                6.7749,
                3.4138,
                6.9157,
                2.6385,
                6.9128
            ],
            "confidence": 0.995,
            "span": {
                "offset": 669,
                "length": 9
            }
        },
        {
            "content": "+",
            "polygon": [
                3.5114,
                6.7632,
                3.6207,
                6.7635,
                3.6209,
                6.9363,
                3.5113,
                6.935
            ],
            "confidence": 0.988,
            "span": {
                "offset": 679,
                "length": 1
            }
        },
        {
            "content": "49",
            "polygon": [
                3.6697,
                6.7629,
                3.8595,
                6.7633,
                3.8598,
                6.9398,
                3.6698,
                6.9368
            ],
            "confidence": 0.992,
            "span": {
                "offset": 681,
                "length": 2
            }
        },
        {
            "content": "42",
            "polygon": [
                3.9516,
                6.7629,
                4.1587,
                6.7631,
                4.1589,
                6.9384,
                3.9517,
                6.939
            ],
            "confidence": 0.971,
            "span": {
                "offset": 684,
                "length": 2
            }
        },
        {
            "content": "19876543",
            "polygon": [
                4.1961,
                6.7632,
                5.1521,
                6.7638,
                5.1521,
                6.9404,
                4.1963,
                6.9385
            ],
            "confidence": 0.952,
            "span": {
                "offset": 687,
                "length": 8
            }
        },
        {
            "content": "Blutgruppe",
            "polygon": [
                2.6929,
                6.9715,
                3.4138,
                6.9768,
                3.4138,
                7.1292,
                2.692,
                7.1257
            ],
            "confidence": 0.995,
            "span": {
                "offset": 696,
                "length": 10
            }
        },
        {
            "content": "A-",
            "polygon": [
                3.5483,
                6.9707,
                3.8356,
                6.9709,
                3.8356,
                7.1431,
                3.5474,
                7.1414
            ],
            "confidence": 0.991,
            "span": {
                "offset": 707,
                "length": 2
            }
        },
        {
            "content": "Gesundheitliche",
            "polygon": [
                1.6926,
                7.1664,
                2.7321,
                7.1676,
                2.7309,
                7.316,
                1.6921,
                7.3119
            ],
            "confidence": 0.994,
            "span": {
                "offset": 710,
                "length": 15
            }
        },
        {
            "content": "Probleme",
            "polygon": [
                2.783,
                7.1678,
                3.4138,
                7.1692,
                3.4138,
                7.3175,
                2.7819,
                7.3159
            ],
            "confidence": 0.996,
            "span": {
                "offset": 726,
                "length": 8
            }
        },
        {
            "content": "Keine",
            "polygon": [
                3.5145,
                7.1754,
                4.0636,
                7.1804,
                4.0636,
                7.3429,
                3.5137,
                7.3408
            ],
            "confidence": 0.996,
            "span": {
                "offset": 735,
                "length": 5
            }
        },
        {
            "content": "Allergien",
            "polygon": [
                2.8217,
                7.3709,
                3.4081,
                7.3741,
                3.4081,
                7.5237,
                2.8208,
                7.5205
            ],
            "confidence": 0.995,
            "span": {
                "offset": 741,
                "length": 9
            }
        },
        {
            "content": "Gluten",
            "polygon": [
                3.5172,
                7.3715,
                4.1317,
                7.3744,
                4.13,
                7.5518,
                3.5162,
                7.5418
            ],
            "confidence": 0.965,
            "span": {
                "offset": 751,
                "length": 6
            }
        },
        {
            "content": "Regelmässig",
            "polygon": [
                1.5093,
                7.565,
                2.3479,
                7.5682,
                2.3463,
                7.7267,
                1.5086,
                7.7245
            ],
            "confidence": 0.993,
            "span": {
                "offset": 758,
                "length": 11
            }
        },
        {
            "content": "eingenommene",
            "polygon": [
                2.3969,
                7.5684,
                3.4081,
                7.5748,
                3.4081,
                7.7247,
                2.3952,
                7.7266
            ],
            "confidence": 0.996,
            "span": {
                "offset": 770,
                "length": 12
            }
        },
        {
            "content": "Medikamente",
            "polygon": [
                2.5212,
                7.7349,
                3.4138,
                7.7391,
                3.4138,
                7.8784,
                2.5218,
                7.8762
            ],
            "confidence": 0.995,
            "span": {
                "offset": 783,
                "length": 11
            }
        },
        {
            "content": "Enzyme",
            "polygon": [
                3.5469,
                7.612,
                4.5423,
                7.6229,
                4.5423,
                7.8398,
                3.5463,
                7.8356
            ],
            "confidence": 0.988,
            "span": {
                "offset": 795,
                "length": 6
            }
        },
        {
            "content": "Informationen",
            "polygon": [
                1.3361,
                7.9167,
                2.5619,
                7.9179,
                2.5618,
                8.0947,
                1.3357,
                8.0932
            ],
            "confidence": 0.993,
            "span": {
                "offset": 802,
                "length": 13
            }
        },
        {
            "content": "für",
            "polygon": [
                2.6256,
                7.9178,
                2.8777,
                7.9166,
                2.8776,
                8.094,
                2.6255,
                8.0943
            ],
            "confidence": 0.959,
            "span": {
                "offset": 816,
                "length": 3
            }
        },
        {
            "content": "den",
            "polygon": [
                2.927,
                7.9164,
                3.2429,
                7.9156,
                3.2427,
                8.093,
                2.9269,
                8.0938
            ],
            "confidence": 0.999,
            "span": {
                "offset": 820,
                "length": 3
            }
        },
        {
            "content": "Notfall",
            "polygon": [
                3.3182,
                7.9157,
                3.8926,
                7.9149,
                3.8926,
                8.0917,
                3.3182,
                8.0923
            ],
            "confidence": 0.994,
            "span": {
                "offset": 824,
                "length": 7
            }
        },
        {
            "content": "Name",
            "polygon": [
                1.5616,
                8.128,
                1.9565,
                8.1279,
                1.9562,
                8.2844,
                1.5614,
                8.2827
            ],
            "confidence": 0.992,
            "span": {
                "offset": 832,
                "length": 4
            }
        },
        {
            "content": "der",
            "polygon": [
                2.0027,
                8.1278,
                2.2155,
                8.1282,
                2.2151,
                8.2859,
                2.0024,
                8.2845
            ],
            "confidence": 0.999,
            "span": {
                "offset": 837,
                "length": 3
            }
        },
        {
            "content": "Kontaktperson",
            "polygon": [
                2.2591,
                8.1286,
                3.1849,
                8.1287,
                3.1838,
                8.2864,
                2.2586,
                8.2861
            ],
            "confidence": 0.994,
            "span": {
                "offset": 841,
                "length": 13
            }
        },
        {
            "content": "für",
            "polygon": [
                3.2284,
                8.1293,
                3.4138,
                8.1309,
                3.4138,
                8.2843,
                3.2275,
                8.2856
            ],
            "confidence": 0.997,
            "span": {
                "offset": 855,
                "length": 3
            }
        },
        {
            "content": "den",
            "polygon": [
                2.6965,
                8.3036,
                2.9367,
                8.3034,
                2.9368,
                8.4446,
                2.6968,
                8.4437
            ],
            "confidence": 0.999,
            "span": {
                "offset": 859,
                "length": 3
            }
        },
        {
            "content": "Notfall",
            "polygon": [
                2.995,
                8.3026,
                3.4081,
                8.3008,
                3.4081,
                8.4435,
                2.9952,
                8.445
            ],
            "confidence": 0.995,
            "span": {
                "offset": 863,
                "length": 7
            }
        },
        {
            "content": "Clara",
            "polygon": [
                3.5222,
                8.1672,
                4.2039,
                8.1734,
                4.2034,
                8.4064,
                3.5217,
                8.4013
            ],
            "confidence": 0.993,
            "span": {
                "offset": 871,
                "length": 5
            }
        },
        {
            "content": "Neumann",
            "polygon": [
                4.338,
                8.1758,
                5.4086,
                8.1933,
                5.4086,
                8.4298,
                4.3374,
                8.4083
            ],
            "confidence": 0.948,
            "span": {
                "offset": 877,
                "length": 7
            }
        },
        {
            "content": "Beziehung",
            "polygon": [
                2.7076,
                8.4791,
                3.4081,
                8.483,
                3.4081,
                8.6304,
                2.7069,
                8.6244
            ],
            "confidence": 0.996,
            "span": {
                "offset": 885,
                "length": 9
            }
        },
        {
            "content": "Mutter",
            "polygon": [
                3.5481,
                8.4662,
                4.2801,
                8.468,
                4.2801,
                8.6589,
                3.5471,
                8.6535
            ],
            "confidence": 0.982,
            "span": {
                "offset": 895,
                "length": 6
            }
        },
        {
            "content": "Adresse",
            "polygon": [
                2.8538,
                8.6778,
                3.4081,
                8.681,
                3.4081,
                8.8151,
                2.8535,
                8.814
            ],
            "confidence": 0.995,
            "span": {
                "offset": 902,
                "length": 7
            }
        },
        {
            "content": "Seestraße",
            "polygon": [
                3.4981,
                8.6635,
                4.5856,
                8.6628,
                4.586,
                8.8457,
                3.4971,
                8.8431
            ],
            "confidence": 0.975,
            "span": {
                "offset": 910,
                "length": 9
            }
        },
        {
            "content": "25",
            "polygon": [
                4.6601,
                8.6621,
                4.9013,
                8.66,
                4.9013,
                8.8427,
                4.6603,
                8.8451
            ],
            "confidence": 0.991,
            "span": {
                "offset": 920,
                "length": 2
            }
        },
        {
            "content": "28",
            "polygon": [
                3.4939,
                8.8526,
                3.7433,
                8.8568,
                3.7429,
                9.0436,
                3.4933,
                9.0423
            ],
            "confidence": 0.996,
            "span": {
                "offset": 923,
                "length": 2
            }
        },
        {
            "content": "195",
            "polygon": [
                3.7981,
                8.8575,
                4.1662,
                8.8622,
                4.1661,
                9.0472,
                3.7976,
                9.0439
            ],
            "confidence": 0.948,
            "span": {
                "offset": 926,
                "length": 3
            }
        },
        {
            "content": "Bremen",
            "polygon": [
                4.2119,
                8.8632,
                4.9412,
                8.8686,
                4.9412,
                9.0508,
                4.2118,
                9.0477
            ],
            "confidence": 0.986,
            "span": {
                "offset": 930,
                "length": 6
            }
        },
        {
            "content": "Rufnummer(n)",
            "polygon": [
                2.4551,
                9.0688,
                3.4024,
                9.0745,
                3.4024,
                9.2248,
                2.4548,
                9.2207
            ],
            "confidence": 0.992,
            "span": {
                "offset": 937,
                "length": 12
            }
        },
        {
            "content": "+",
            "polygon": [
                3.4908,
                9.0597,
                3.5831,
                9.0612,
                3.5827,
                9.2409,
                3.4906,
                9.2402
            ],
            "confidence": 0.988,
            "span": {
                "offset": 950,
                "length": 1
            }
        },
        {
            "content": "49",
            "polygon": [
                3.6397,
                9.0612,
                3.8422,
                9.059,
                3.842,
                9.244,
                3.6392,
                9.2417
            ],
            "confidence": 0.994,
            "span": {
                "offset": 952,
                "length": 2
            }
        },
        {
            "content": "42",
            "polygon": [
                3.9285,
                9.0588,
                4.1191,
                9.0595,
                4.1192,
                9.2424,
                3.9285,
                9.2436
            ],
            "confidence": 0.998,
            "span": {
                "offset": 955,
                "length": 2
            }
        },
        {
            "content": "12",
            "polygon": [
                4.1638,
                9.0593,
                4.405,
                9.0613,
                4.4052,
                9.2426,
                4.164,
                9.2424
            ],
            "confidence": 0.998,
            "span": {
                "offset": 958,
                "length": 2
            }
        },
        {
            "content": "345678",
            "polygon": [
                4.4616,
                9.0608,
                5.1977,
                9.063,
                5.1977,
                9.2422,
                4.4618,
                9.2424
            ],
            "confidence": 0.991,
            "span": {
                "offset": 961,
                "length": 6
            }
        }
    ],
    "lines": [
        {
            "content": "Formular mit Mitarbeiterinformationen für den Notfall",
            "polygon": [
                1.3527,
                1.2191,
                6.7147,
                1.2153,
                6.7148,
                1.4162,
                1.3528,
                1.4185
            ],
            "spans": [
                {
                    "offset": 0,
                    "length": 53
                }
            ]
        },
        {
            "content": "Zuletzt aktualisiert: 21.10.2024",
            "polygon": [
                1.3445,
                1.6097,
                3.3492,
                1.6101,
                3.3492,
                1.7544,
                1.3445,
                1.754
            ],
            "spans": [
                {
                    "offset": 54,
                    "length": 32
                }
            ]
        },
        {
            "content": "Persönliche Informationen",
            "polygon": [
                1.3502,
                1.9539,
                3.6962,
                1.9649,
                3.6954,
                2.1348,
                1.3494,
                2.1238
            ],
            "spans": [
                {
                    "offset": 87,
                    "length": 25
                }
            ]
        },
        {
            "content": "Mitarbeiternummer",
            "polygon": [
                2.1855,
                2.1708,
                3.4194,
                2.1754,
                3.4189,
                2.3151,
                2.185,
                2.3104
            ],
            "spans": [
                {
                    "offset": 113,
                    "length": 17
                }
            ]
        },
        {
            "content": "96731",
            "polygon": [
                3.5286,
                2.1662,
                4.1707,
                2.1675,
                4.1704,
                2.3449,
                3.5282,
                2.3436
            ],
            "spans": [
                {
                    "offset": 131,
                    "length": 5
                }
            ]
        },
        {
            "content": "Vorname",
            "polygon": [
                2.8073,
                2.3761,
                3.4218,
                2.3796,
                3.421,
                2.5099,
                2.8065,
                2.5063
            ],
            "spans": [
                {
                    "offset": 137,
                    "length": 7
                }
            ]
        },
        {
            "content": "Nina",
            "polygon": [
                3.5412,
                2.385,
                4.0579,
                2.39,
                4.0572,
                2.5521,
                3.5397,
                2.5472
            ],
            "spans": [
                {
                    "offset": 145,
                    "length": 4
                }
            ]
        },
        {
            "content": "Zweiter Vorname",
            "polygon": [
                2.2931,
                2.5692,
                3.421,
                2.5716,
                3.4207,
                2.7154,
                2.2928,
                2.7128
            ],
            "spans": [
                {
                    "offset": 150,
                    "length": 15
                }
            ]
        },
        {
            "content": "Luise",
            "polygon": [
                3.5216,
                2.5749,
                4.0488,
                2.582,
                4.0463,
                2.7489,
                3.5191,
                2.741
            ],
            "spans": [
                {
                    "offset": 166,
                    "length": 5
                }
            ]
        },
        {
            "content": "Nachname",
            "polygon": [
                2.6995,
                2.772,
                3.4188,
                2.7749,
                3.4182,
                2.9106,
                2.699,
                2.9076
            ],
            "spans": [
                {
                    "offset": 172,
                    "length": 8
                }
            ]
        },
        {
            "content": "Neumann",
            "polygon": [
                3.5544,
                2.7856,
                4.5024,
                2.7981,
                4.5012,
                2.9508,
                3.5523,
                2.9413
            ],
            "spans": [
                {
                    "offset": 181,
                    "length": 7
                }
            ]
        },
        {
            "content": "Rufname",
            "polygon": [
                2.8135,
                2.9704,
                3.4202,
                2.973,
                3.4196,
                3.109,
                2.813,
                3.1064
            ],
            "spans": [
                {
                    "offset": 189,
                    "length": 7
                }
            ]
        },
        {
            "content": "Vini",
            "polygon": [
                3.564,
                2.9911,
                4.0147,
                2.9974,
                4.0126,
                3.1494,
                3.562,
                3.1431
            ],
            "spans": [
                {
                    "offset": 197,
                    "length": 4
                }
            ]
        },
        {
            "content": "Geschlecht",
            "polygon": [
                2.6775,
                3.1685,
                3.4243,
                3.1687,
                3.4243,
                3.3077,
                2.6775,
                3.3075
            ],
            "spans": [
                {
                    "offset": 202,
                    "length": 10
                }
            ]
        },
        {
            "content": "F",
            "polygon": [
                3.5502,
                3.1675,
                3.6871,
                3.1684,
                3.686,
                3.3258,
                3.5491,
                3.3249
            ],
            "spans": [
                {
                    "offset": 213,
                    "length": 1
                }
            ]
        },
        {
            "content": "Nationalität",
            "polygon": [
                2.6729,
                3.3666,
                3.4202,
                3.3669,
                3.4201,
                3.5054,
                2.6729,
                3.505
            ],
            "spans": [
                {
                    "offset": 215,
                    "length": 12
                }
            ]
        },
        {
            "content": "Deutsch",
            "polygon": [
                3.5115,
                3.3454,
                4.2218,
                3.3502,
                4.2205,
                3.538,
                3.5107,
                3.5332
            ],
            "spans": [
                {
                    "offset": 228,
                    "length": 7
                }
            ]
        },
        {
            "content": "Geburtsort (Land)",
            "polygon": [
                2.2554,
                3.5604,
                3.4138,
                3.5638,
                3.4135,
                3.7193,
                2.2549,
                3.7158
            ],
            "spans": [
                {
                    "offset": 236,
                    "length": 17
                }
            ]
        },
        {
            "content": "Bremen",
            "polygon": [
                3.5065,
                3.5561,
                4.2402,
                3.5655,
                4.2389,
                3.748,
                3.5042,
                3.7386
            ],
            "spans": [
                {
                    "offset": 254,
                    "length": 6
                }
            ]
        },
        {
            "content": "Anschrift privat",
            "polygon": [
                2.4349,
                3.7633,
                3.4219,
                3.7661,
                3.4215,
                3.9173,
                2.4345,
                3.9145
            ],
            "spans": [
                {
                    "offset": 261,
                    "length": 16
                }
            ]
        },
        {
            "content": "Seestraße 25",
            "polygon": [
                3.5019,
                3.7591,
                4.8601,
                3.7552,
                4.8606,
                3.9348,
                3.5024,
                3.9364
            ],
            "spans": [
                {
                    "offset": 278,
                    "length": 12
                }
            ]
        },
        {
            "content": "28195 Bremen",
            "polygon": [
                3.5161,
                3.9574,
                4.8751,
                3.9661,
                4.874,
                4.1357,
                3.515,
                4.1301
            ],
            "spans": [
                {
                    "offset": 291,
                    "length": 12
                }
            ]
        },
        {
            "content": "Bundesland/Kanton",
            "polygon": [
                2.133,
                4.159,
                3.4157,
                4.1609,
                3.4155,
                4.3078,
                2.1328,
                4.3059
            ],
            "spans": [
                {
                    "offset": 304,
                    "length": 17
                }
            ]
        },
        {
            "content": "Bremen",
            "polygon": [
                3.5363,
                4.1542,
                4.2658,
                4.1636,
                4.2635,
                4.3408,
                3.534,
                4.3333
            ],
            "spans": [
                {
                    "offset": 322,
                    "length": 6
                }
            ]
        },
        {
            "content": "Telefon privat",
            "polygon": [
                2.5223,
                4.3586,
                3.4195,
                4.3616,
                3.419,
                4.5135,
                2.5218,
                4.5105
            ],
            "spans": [
                {
                    "offset": 329,
                    "length": 14
                }
            ]
        },
        {
            "content": "+494211230987",
            "polygon": [
                3.502,
                4.3499,
                5.1503,
                4.3469,
                5.1506,
                4.5244,
                3.5023,
                4.5274
            ],
            "spans": [
                {
                    "offset": 344,
                    "length": 13
                }
            ]
        },
        {
            "content": "Handy",
            "polygon": [
                2.9782,
                4.5559,
                3.4117,
                4.5596,
                3.4104,
                4.7135,
                2.9769,
                4.7098
            ],
            "spans": [
                {
                    "offset": 358,
                    "length": 5
                }
            ]
        },
        {
            "content": "+ 491711230987",
            "polygon": [
                3.5119,
                4.5484,
                5.149,
                4.5483,
                5.149,
                4.7273,
                3.5119,
                4.7275
            ],
            "spans": [
                {
                    "offset": 364,
                    "length": 14
                }
            ]
        },
        {
            "content": "Fax privat",
            "polygon": [
                2.7594,
                4.7591,
                3.4192,
                4.7608,
                3.4188,
                4.9131,
                2.759,
                4.9115
            ],
            "spans": [
                {
                    "offset": 379,
                    "length": 10
                }
            ]
        },
        {
            "content": "+49 4211 230988",
            "polygon": [
                3.5257,
                4.7438,
                5.1358,
                4.7466,
                5.1355,
                4.9269,
                3.5253,
                4.9241
            ],
            "spans": [
                {
                    "offset": 390,
                    "length": 15
                }
            ]
        },
        {
            "content": "E-Mail-Adresse privat",
            "polygon": [
                2.0087,
                4.9538,
                3.4177,
                4.9593,
                3.4171,
                5.1111,
                2.0081,
                5.1056
            ],
            "spans": [
                {
                    "offset": 406,
                    "length": 21
                }
            ]
        },
        {
            "content": "nina.neumann@example.com",
            "polygon": [
                3.5454,
                4.9641,
                6.5329,
                4.9695,
                6.5326,
                5.1479,
                3.5451,
                5.1425
            ],
            "spans": [
                {
                    "offset": 428,
                    "length": 24
                }
            ]
        },
        {
            "content": "Geburtstag (TT/MM/JJJJ)",
            "polygon": [
                1.7498,
                5.1526,
                3.4076,
                5.1546,
                3.4074,
                5.314,
                1.7496,
                5.312
            ],
            "spans": [
                {
                    "offset": 453,
                    "length": 23
                }
            ]
        },
        {
            "content": "1996-01-05",
            "polygon": [
                3.5233,
                5.1663,
                4.8143,
                5.166,
                4.8143,
                5.3291,
                3.5233,
                5.3294
            ],
            "spans": [
                {
                    "offset": 477,
                    "length": 10
                }
            ]
        },
        {
            "content": "Sozialversicherungsnummer",
            "polygon": [
                1.5606,
                5.3515,
                3.4124,
                5.361,
                3.4116,
                5.5125,
                1.5598,
                5.5029
            ],
            "spans": [
                {
                    "offset": 488,
                    "length": 25
                }
            ]
        },
        {
            "content": "567890123",
            "polygon": [
                3.5198,
                5.3548,
                4.5942,
                5.3603,
                4.5931,
                5.5282,
                3.5186,
                5.5207
            ],
            "spans": [
                {
                    "offset": 514,
                    "length": 9
                }
            ]
        },
        {
            "content": "Ausweisnummer",
            "polygon": [
                2.3161,
                5.5558,
                3.4142,
                5.5593,
                3.4138,
                5.6999,
                2.3157,
                5.6964
            ],
            "spans": [
                {
                    "offset": 524,
                    "length": 13
                }
            ]
        },
        {
            "content": "356789012",
            "polygon": [
                3.4946,
                5.5532,
                4.5525,
                5.5551,
                4.5522,
                5.7235,
                3.4943,
                5.7216
            ],
            "spans": [
                {
                    "offset": 538,
                    "length": 9
                }
            ]
        },
        {
            "content": "Führerscheinnummer",
            "polygon": [
                2.017,
                5.7536,
                3.4137,
                5.7588,
                3.4131,
                5.9012,
                2.0164,
                5.895
            ],
            "spans": [
                {
                    "offset": 548,
                    "length": 18
                }
            ]
        },
        {
            "content": "M56789012",
            "polygon": [
                3.5008,
                5.7529,
                4.753,
                5.7522,
                4.7531,
                5.9212,
                3.5009,
                5.922
            ],
            "spans": [
                {
                    "offset": 567,
                    "length": 9
                }
            ]
        },
        {
            "content": "Medizinische Informationen",
            "polygon": [
                1.3402,
                5.9567,
                3.7875,
                5.9658,
                3.7869,
                6.1353,
                1.3396,
                6.1284
            ],
            "spans": [
                {
                    "offset": 577,
                    "length": 26
                }
            ]
        },
        {
            "content": "Name des Arztes",
            "polygon": [
                2.2799,
                6.1712,
                3.4095,
                6.174,
                3.4091,
                6.3198,
                2.2795,
                6.317
            ],
            "spans": [
                {
                    "offset": 604,
                    "length": 15
                }
            ]
        },
        {
            "content": "Dr. Martin Weiss",
            "polygon": [
                3.5567,
                6.1528,
                5.3067,
                6.1602,
                5.3058,
                6.3548,
                3.5559,
                6.3474
            ],
            "spans": [
                {
                    "offset": 620,
                    "length": 16
                }
            ]
        },
        {
            "content": "Adresse",
            "polygon": [
                2.857,
                6.3764,
                3.4114,
                6.3794,
                3.4106,
                6.5145,
                2.8563,
                6.5115
            ],
            "spans": [
                {
                    "offset": 637,
                    "length": 7
                }
            ]
        },
        {
            "content": "Altstadt 1",
            "polygon": [
                3.53,
                6.3732,
                4.6032,
                6.3664,
                4.6043,
                6.547,
                3.5312,
                6.5538
            ],
            "spans": [
                {
                    "offset": 645,
                    "length": 10
                }
            ]
        },
        {
            "content": "28195 Bremen",
            "polygon": [
                3.5175,
                6.5575,
                4.9335,
                6.573,
                4.9315,
                6.756,
                3.5154,
                6.7405
            ],
            "spans": [
                {
                    "offset": 656,
                    "length": 12
                }
            ]
        },
        {
            "content": "Rufnummer",
            "polygon": [
                2.639,
                6.7696,
                3.4121,
                6.7746,
                3.4112,
                6.9157,
                2.6381,
                6.9108
            ],
            "spans": [
                {
                    "offset": 669,
                    "length": 9
                }
            ]
        },
        {
            "content": "+ 49 42 19876543",
            "polygon": [
                3.5114,
                6.7613,
                5.152,
                6.7639,
                5.1517,
                6.9399,
                3.5112,
                6.9373
            ],
            "spans": [
                {
                    "offset": 679,
                    "length": 16
                }
            ]
        },
        {
            "content": "Blutgruppe",
            "polygon": [
                2.6929,
                6.9699,
                3.4119,
                6.9766,
                3.4105,
                7.1305,
                2.6915,
                7.1239
            ],
            "spans": [
                {
                    "offset": 696,
                    "length": 10
                }
            ]
        },
        {
            "content": "A-",
            "polygon": [
                3.548,
                6.9698,
                3.8301,
                6.9708,
                3.8295,
                7.1415,
                3.5474,
                7.1405
            ],
            "spans": [
                {
                    "offset": 707,
                    "length": 2
                }
            ]
        },
        {
            "content": "Gesundheitliche Probleme",
            "polygon": [
                1.6925,
                7.1638,
                3.4111,
                7.1682,
                3.4107,
                7.3156,
                1.6921,
                7.3112
            ],
            "spans": [
                {
                    "offset": 710,
                    "length": 24
                }
            ]
        },
        {
            "content": "Keine",
            "polygon": [
                3.5143,
                7.1751,
                4.0582,
                7.1772,
                4.0576,
                7.3421,
                3.5137,
                7.34
            ],
            "spans": [
                {
                    "offset": 735,
                    "length": 5
                }
            ]
        },
        {
            "content": "Allergien",
            "polygon": [
                2.8217,
                7.3697,
                3.404,
                7.3734,
                3.403,
                7.5236,
                2.8207,
                7.5199
            ],
            "spans": [
                {
                    "offset": 741,
                    "length": 9
                }
            ]
        },
        {
            "content": "Gluten",
            "polygon": [
                3.5172,
                7.3684,
                4.1269,
                7.3743,
                4.1252,
                7.5488,
                3.5155,
                7.5428
            ],
            "spans": [
                {
                    "offset": 751,
                    "length": 6
                }
            ]
        },
        {
            "content": "Regelmässig eingenommene",
            "polygon": [
                1.5092,
                7.5641,
                3.4067,
                7.5712,
                3.4061,
                7.7303,
                1.5086,
                7.7231
            ],
            "spans": [
                {
                    "offset": 758,
                    "length": 24
                }
            ]
        },
        {
            "content": "Medikamente",
            "polygon": [
                2.5212,
                7.734,
                3.4115,
                7.7373,
                3.411,
                7.8772,
                2.5207,
                7.8739
            ],
            "spans": [
                {
                    "offset": 783,
                    "length": 11
                }
            ]
        },
        {
            "content": "Enzyme",
            "polygon": [
                3.5469,
                7.611,
                4.5423,
                7.6212,
                4.5407,
                7.8421,
                3.5449,
                7.8319
            ],
            "spans": [
                {
                    "offset": 795,
                    "length": 6
                }
            ]
        },
        {
            "content": "Informationen für den Notfall",
            "polygon": [
                1.3356,
                7.9167,
                3.8884,
                7.9148,
                3.8886,
                8.0918,
                1.3357,
                8.0937
            ],
            "spans": [
                {
                    "offset": 802,
                    "length": 29
                }
            ]
        },
        {
            "content": "Name der Kontaktperson für",
            "polygon": [
                1.5616,
                8.1268,
                3.4084,
                8.1283,
                3.4083,
                8.2847,
                1.5614,
                8.2831
            ],
            "spans": [
                {
                    "offset": 832,
                    "length": 26
                }
            ]
        },
        {
            "content": "den Notfall",
            "polygon": [
                2.6962,
                8.3029,
                3.4069,
                8.3,
                3.4075,
                8.4417,
                2.6968,
                8.4446
            ],
            "spans": [
                {
                    "offset": 859,
                    "length": 11
                }
            ]
        },
        {
            "content": "Clara Neumann",
            "polygon": [
                3.5222,
                8.1632,
                5.4073,
                8.1918,
                5.4037,
                8.4262,
                3.5187,
                8.3974
            ],
            "spans": [
                {
                    "offset": 871,
                    "length": 13
                }
            ]
        },
        {
            "content": "Beziehung",
            "polygon": [
                2.7076,
                8.4782,
                3.4042,
                8.4829,
                3.4032,
                8.6294,
                2.7067,
                8.6248
            ],
            "spans": [
                {
                    "offset": 885,
                    "length": 9
                }
            ]
        },
        {
            "content": "Mutter",
            "polygon": [
                3.5481,
                8.4632,
                4.2772,
                8.4677,
                4.276,
                8.6589,
                3.5469,
                8.6556
            ],
            "spans": [
                {
                    "offset": 895,
                    "length": 6
                }
            ]
        },
        {
            "content": "Adresse",
            "polygon": [
                2.8538,
                8.6772,
                3.4068,
                8.6812,
                3.4059,
                8.8161,
                2.8528,
                8.8122
            ],
            "spans": [
                {
                    "offset": 902,
                    "length": 7
                }
            ]
        },
        {
            "content": "Seestraße 25",
            "polygon": [
                3.4967,
                8.6631,
                4.8959,
                8.6592,
                4.8964,
                8.8422,
                3.4972,
                8.8462
            ],
            "spans": [
                {
                    "offset": 910,
                    "length": 12
                }
            ]
        },
        {
            "content": "28 195 Bremen",
            "polygon": [
                3.4939,
                8.8526,
                4.9389,
                8.8688,
                4.9368,
                9.0519,
                3.4918,
                9.0392
            ],
            "spans": [
                {
                    "offset": 923,
                    "length": 13
                }
            ]
        },
        {
            "content": "Rufnummer(n)",
            "polygon": [
                2.4551,
                9.0688,
                3.4004,
                9.0739,
                3.3996,
                9.2233,
                2.4543,
                9.2182
            ],
            "spans": [
                {
                    "offset": 937,
                    "length": 12
                }
            ]
        },
        {
            "content": "+ 49 42 12 345678",
            "polygon": [
                3.4905,
                9.059,
                5.1941,
                9.0579,
                5.1943,
                9.2402,
                3.4906,
                9.2413
            ],
            "spans": [
                {
                    "offset": 950,
                    "length": 17
                }
            ]
        }
    ],
    "spans": [
        {
            "offset": 0,
            "length": 967
        }
    ]
}