{
    "pageNumber": 1,
    "angle": -0.016699999570846558,
    "width": 8.2639,
    "height": 11.6667,
    "unit": "inch",
    "words": [
        {
            "content": "MusterTech",
            "polygon": [
                0.9172,
                0.9876,
                1.8322,
                0.9856,
                1.8319,
                1.1383,
                0.9172,
                1.1381
            ],
            "confidence": 0.995,
            "span": {
                "offset": 0,
                "length": 10
            }
        },
        {
            "content": "GmbH",
            "polygon": [
                1.8921,
                0.9854,
                2.3823,
                0.983,
                2.3823,
                1.1369,
                1.8918,
                1.138
            ],
            "confidence": 0.991,
            "span": {
                "offset": 11,
                "length": 4
            }
        },
        {
            "content": "Ihre",
            "polygon": [
                0.9195,
                1.1752,
                1.1338,
                1.1758,
                1.1338,
                1.3049,
                0.9196,
                1.3047
            ],
            "confidence": 0.988,
            "span": {
                "offset": 16,
                "length": 4
            }
        },
        {
            "content": "Technik",
            "polygon": [
                1.1836,
                1.1758,
                1.6121,
                1.1749,
                1.6117,
                1.3064,
                1.1835,
                1.305
            ],
            "confidence": 0.996,
            "span": {
                "offset": 21,
                "length": 7
            }
        },
        {
            "content": "-",
            "polygon": [
                1.6402,
                1.1749,
                1.716,
                1.1748,
                1.7155,
                1.3065,
                1.6398,
                1.3065
            ],
            "confidence": 0.988,
            "span": {
                "offset": 29,
                "length": 1
            }
        },
        {
            "content": "Unser",
            "polygon": [
                1.7614,
                1.1747,
                2.0796,
                1.1752,
                2.0792,
                1.3066,
                1.761,
                1.3065
            ],
            "confidence": 0.998,
            "span": {
                "offset": 31,
                "length": 5
            }
        },
        {
            "content": "Muster",
            "polygon": [
                2.1055,
                1.1752,
                2.5081,
                1.1748,
                2.5072,
                1.3085,
                2.1052,
                1.3069
            ],
            "confidence": 0.998,
            "span": {
                "offset": 37,
                "length": 6
            }
        },
        {
            "content": "für",
            "polygon": [
                2.534,
                1.1749,
                2.6899,
                1.1752,
                2.689,
                1.3083,
                2.5332,
                1.3084
            ],
            "confidence": 0.998,
            "span": {
                "offset": 44,
                "length": 3
            }
        },
        {
            "content": "Erfolg.",
            "polygon": [
                2.7223,
                1.1751,
                3.0719,
                1.175,
                3.0719,
                1.3102,
                2.7214,
                1.3084
            ],
            "confidence": 0.995,
            "span": {
                "offset": 48,
                "length": 7
            }
        },
        {
            "content": "RECHNUNG",
            "polygon": [
                5.6848,
                0.9986,
                7.2437,
                0.9937,
                7.2437,
                1.233,
                5.6843,
                1.2362
            ],
            "confidence": 0.995,
            "span": {
                "offset": 56,
                "length": 8
            }
        },
        {
            "content": "Musterstraße",
            "polygon": [
                0.9158,
                1.491,
                1.6487,
                1.491,
                1.6481,
                1.6138,
                0.9157,
                1.6133
            ],
            "confidence": 0.992,
            "span": {
                "offset": 65,
                "length": 12
            }
        },
        {
            "content": "123",
            "polygon": [
                1.699,
                1.491,
                1.9035,
                1.4907,
                1.9035,
                1.6141,
                1.6983,
                1.6135
            ],
            "confidence": 0.994,
            "span": {
                "offset": 78,
                "length": 3
            }
        },
        {
            "content": "12345",
            "polygon": [
                0.9275,
                1.644,
                1.2594,
                1.6442,
                1.2591,
                1.7637,
                0.9277,
                1.7621
            ],
            "confidence": 0.997,
            "span": {
                "offset": 82,
                "length": 5
            }
        },
        {
            "content": "Musterstadt",
            "polygon": [
                1.3063,
                1.6445,
                1.9662,
                1.6458,
                1.9662,
                1.7644,
                1.306,
                1.7639
            ],
            "confidence": 0.995,
            "span": {
                "offset": 88,
                "length": 11
            }
        },
        {
            "content": "+4912345678",
            "polygon": [
                0.9224,
                1.7998,
                1.6927,
                1.7974,
                1.6927,
                1.9134,
                0.9222,
                1.9132
            ],
            "confidence": 0.993,
            "span": {
                "offset": 100,
                "length": 11
            }
        },
        {
            "content": "RECHNUNGSNR.",
            "polygon": [
                5.9898,
                1.572,
                6.9886,
                1.5707,
                6.988,
                1.6965,
                5.9897,
                1.6976
            ],
            "confidence": 0.995,
            "span": {
                "offset": 112,
                "length": 12
            }
        },
        {
            "content": "123",
            "polygon": [
                7.0443,
                1.5708,
                7.2494,
                1.5702,
                7.2494,
                1.6955,
                7.0438,
                1.6962
            ],
            "confidence": 0.998,
            "span": {
                "offset": 125,
                "length": 3
            }
        },
        {
            "content": "DATUM:",
            "polygon": [
                6.1045,
                1.7252,
                6.5702,
                1.7241,
                6.5701,
                1.8478,
                6.1047,
                1.8481
            ],
            "confidence": 0.995,
            "span": {
                "offset": 129,
                "length": 6
            }
        },
        {
            "content": "16.10.2024",
            "polygon": [
                6.6246,
                1.7238,
                7.2551,
                1.7237,
                7.2551,
                1.8463,
                6.6245,
                1.8479
            ],
            "confidence": 0.995,
            "span": {
                "offset": 136,
                "length": 10
            }
        },
        {
            "content": "AN:",
            "polygon": [
                0.9158,
                2.0422,
                1.1398,
                2.0421,
                1.1398,
                2.1555,
                0.9152,
                2.1545
            ],
            "confidence": 0.995,
            "span": {
                "offset": 147,
                "length": 3
            }
        },
        {
            "content": "Herr",
            "polygon": [
                0.917,
                2.1911,
                1.165,
                2.1914,
                1.164,
                2.3143,
                0.9162,
                2.313
            ],
            "confidence": 0.992,
            "span": {
                "offset": 151,
                "length": 4
            }
        },
        {
            "content": "Michael",
            "polygon": [
                1.2036,
                2.1915,
                1.6202,
                2.1915,
                1.6185,
                2.3156,
                1.2024,
                2.3147
            ],
            "confidence": 0.996,
            "span": {
                "offset": 156,
                "length": 7
            }
        },
        {
            "content": "Buchhalter",
            "polygon": [
                1.671,
                2.1911,
                2.2797,
                2.1908,
                2.2797,
                2.3151,
                1.6692,
                2.3157
            ],
            "confidence": 0.995,
            "span": {
                "offset": 164,
                "length": 10
            }
        },
        {
            "content": "Testlogistik",
            "polygon": [
                0.9153,
                2.3423,
                1.5456,
                2.342,
                1.5448,
                2.4723,
                0.9147,
                2.4723
            ],
            "confidence": 0.995,
            "span": {
                "offset": 175,
                "length": 12
            }
        },
        {
            "content": "AG",
            "polygon": [
                1.5817,
                2.3412,
                1.7668,
                2.3438,
                1.7668,
                2.4718,
                1.5811,
                2.4723
            ],
            "confidence": 0.962,
            "span": {
                "offset": 188,
                "length": 2
            }
        },
        {
            "content": "Testweg",
            "polygon": [
                0.9171,
                2.4961,
                1.3799,
                2.4974,
                1.3794,
                2.6245,
                0.9163,
                2.622
            ],
            "confidence": 0.996,
            "span": {
                "offset": 191,
                "length": 7
            }
        },
        {
            "content": "456",
            "polygon": [
                1.4216,
                2.4974,
                1.6414,
                2.4967,
                1.6414,
                2.6244,
                1.4212,
                2.6242
            ],
            "confidence": 0.997,
            "span": {
                "offset": 199,
                "length": 3
            }
        },
        {
            "content": "67890",
            "polygon": [
                0.9145,
                2.6476,
                1.2591,
                2.6486,
                1.2578,
                2.769,
                0.914,
                2.7667
            ],
            "confidence": 0.998,
            "span": {
                "offset": 203,
                "length": 5
            }
        },
        {
            "content": "Testhausen",
            "polygon": [
                1.2985,
                2.6489,
                1.9548,
                2.6519,
                1.9548,
                2.771,
                1.2973,
                2.7692
            ],
            "confidence": 0.996,
            "span": {
                "offset": 209,
                "length": 10
            }
        },
        {
            "content": "+4987654321",
            "polygon": [
                0.9187,
                2.7988,
                1.6756,
                2.799,
                1.6756,
                2.9196,
                0.9186,
                2.9178
            ],
            "confidence": 0.993,
            "span": {
                "offset": 220,
                "length": 11
            }
        },
        {
            "content": "LIEFERADRESSE:",
            "polygon": [
                4.2525,
                2.0316,
                5.3402,
                2.0313,
                5.3402,
                2.1565,
                4.2525,
                2.1548
            ],
            "confidence": 0.992,
            "span": {
                "offset": 232,
                "length": 14
            }
        },
        {
            "content": "Frau",
            "polygon": [
                4.2529,
                2.1874,
                4.5065,
                2.1878,
                4.5063,
                2.3129,
                4.2527,
                2.3118
            ],
            "confidence": 0.992,
            "span": {
                "offset": 247,
                "length": 4
            }
        },
        {
            "content": "Sabine",
            "polygon": [
                4.5519,
                2.1879,
                4.9314,
                2.1879,
                4.931,
                2.3145,
                4.5516,
                2.313
            ],
            "confidence": 0.998,
            "span": {
                "offset": 252,
                "length": 6
            }
        },
        {
            "content": "Logistik",
            "polygon": [
                4.9768,
                2.1884,
                5.4078,
                2.1882,
                5.4074,
                2.3138,
                4.9765,
                2.3146
            ],
            "confidence": 0.996,
            "span": {
                "offset": 259,
                "length": 8
            }
        },
        {
            "content": "Testlogistik",
            "polygon": [
                4.2523,
                2.3388,
                4.8835,
                2.3384,
                4.8829,
                2.4691,
                4.2518,
                2.469
            ],
            "confidence": 0.995,
            "span": {
                "offset": 268,
                "length": 12
            }
        },
        {
            "content": "AG",
            "polygon": [
                4.9173,
                2.3381,
                5.1065,
                2.3389,
                5.1065,
                2.4682,
                4.9169,
                2.4689
            ],
            "confidence": 0.997,
            "span": {
                "offset": 281,
                "length": 2
            }
        },
        {
            "content": "Teststraße",
            "polygon": [
                4.2535,
                2.4927,
                4.8493,
                2.4928,
                4.8488,
                2.6128,
                4.2531,
                2.6124
            ],
            "confidence": 0.994,
            "span": {
                "offset": 284,
                "length": 10
            }
        },
        {
            "content": "42",
            "polygon": [
                4.8884,
                2.493,
                5.0324,
                2.4928,
                5.0324,
                2.6138,
                4.8878,
                2.6128
            ],
            "confidence": 0.998,
            "span": {
                "offset": 295,
                "length": 2
            }
        },
        {
            "content": "09999",
            "polygon": [
                4.2525,
                2.6396,
                4.5991,
                2.6413,
                4.5987,
                2.7629,
                4.252,
                2.7629
            ],
            "confidence": 0.997,
            "span": {
                "offset": 298,
                "length": 5
            }
        },
        {
            "content": "Testdorf",
            "polygon": [
                4.6354,
                2.6413,
                5.1151,
                2.641,
                5.1145,
                2.7629,
                4.6351,
                2.7629
            ],
            "confidence": 0.995,
            "span": {
                "offset": 304,
                "length": 8
            }
        },
        {
            "content": "Telefon:",
            "polygon": [
                4.2512,
                2.7925,
                4.6953,
                2.7924,
                4.6955,
                2.9167,
                4.2511,
                2.9167
            ],
            "confidence": 0.994,
            "span": {
                "offset": 313,
                "length": 8
            }
        },
        {
            "content": "+4987654322",
            "polygon": [
                4.7447,
                2.7922,
                5.5169,
                2.7892,
                5.5169,
                2.9167,
                4.7448,
                2.9167
            ],
            "confidence": 0.994,
            "span": {
                "offset": 322,
                "length": 11
            }
        },
        {
            "content": "KOMMENTARE",
            "polygon": [
                0.9167,
                3.2073,
                1.8162,
                3.2051,
                1.8154,
                3.3382,
                0.9165,
                3.3373
            ],
            "confidence": 0.992,
            "span": {
                "offset": 334,
                "length": 10
            }
        },
        {
            "content": "ODER",
            "polygon": [
                1.8598,
                3.2051,
                2.2061,
                3.2045,
                2.205,
                3.3382,
                1.859,
                3.3382
            ],
            "confidence": 0.992,
            "span": {
                "offset": 345,
                "length": 4
            }
        },
        {
            "content": "BESONDERE",
            "polygon": [
                2.2496,
                3.2044,
                3.0163,
                3.2039,
                3.0157,
                3.3371,
                2.2485,
                3.3382
            ],
            "confidence": 0.993,
            "span": {
                "offset": 350,
                "length": 9
            }
        },
        {
            "content": "ANWEISUNGEN:",
            "polygon": [
                3.0576,
                3.204,
                4.0408,
                3.2013,
                4.0408,
                3.3352,
                3.0572,
                3.3373
            ],
            "confidence": 0.992,
            "span": {
                "offset": 360,
                "length": 12
            }
        },
        {
            "content": "Bitte",
            "polygon": [
                0.9176,
                3.3567,
                1.1687,
                3.3576,
                1.1689,
                3.497,
                0.9177,
                3.4956
            ],
            "confidence": 0.998,
            "span": {
                "offset": 373,
                "length": 5
            }
        },
        {
            "content": "alle",
            "polygon": [
                1.2114,
                3.3578,
                1.4009,
                3.3582,
                1.401,
                3.4981,
                1.2115,
                3.4972
            ],
            "confidence": 0.989,
            "span": {
                "offset": 379,
                "length": 4
            }
        },
        {
            "content": "Geräte",
            "polygon": [
                1.4483,
                3.3581,
                1.8178,
                3.3573,
                1.8177,
                3.4988,
                1.4484,
                3.4981
            ],
            "confidence": 0.995,
            "span": {
                "offset": 384,
                "length": 6
            }
        },
        {
            "content": "vor",
            "polygon": [
                1.8605,
                3.3574,
                2.0334,
                3.3578,
                2.0333,
                3.4992,
                1.8604,
                3.4989
            ],
            "confidence": 0.999,
            "span": {
                "offset": 391,
                "length": 3
            }
        },
        {
            "content": "der",
            "polygon": [
                2.0689,
                3.3578,
                2.2348,
                3.3582,
                2.2347,
                3.4996,
                2.0688,
                3.4993
            ],
            "confidence": 0.999,
            "span": {
                "offset": 395,
                "length": 3
            }
        },
        {
            "content": "Inbetriebnahme",
            "polygon": [
                2.2632,
                3.3581,
                3.1421,
                3.3563,
                3.1421,
                3.5006,
                2.2631,
                3.4996
            ],
            "confidence": 0.994,
            "span": {
                "offset": 399,
                "length": 14
            }
        },
        {
            "content": "gründlich",
            "polygon": [
                3.1824,
                3.3562,
                3.6822,
                3.3545,
                3.6821,
                3.5015,
                3.1824,
                3.5007
            ],
            "confidence": 0.996,
            "span": {
                "offset": 414,
                "length": 9
            }
        },
        {
            "content": "prüfen.",
            "polygon": [
                3.7296,
                3.3543,
                4.1039,
                3.3533,
                4.1038,
                3.501,
                3.7295,
                3.5015
            ],
            "confidence": 0.996,
            "span": {
                "offset": 424,
                "length": 7
            }
        },
        {
            "content": "Verpackungsmaterial",
            "polygon": [
                4.156,
                3.3534,
                5.3239,
                3.3536,
                5.3233,
                3.4998,
                4.1559,
                3.5009
            ],
            "confidence": 0.994,
            "span": {
                "offset": 432,
                "length": 19
            }
        },
        {
            "content": "bitte",
            "polygon": [
                5.3689,
                3.3536,
                5.6011,
                3.3535,
                5.6005,
                3.4994,
                5.3683,
                3.4998
            ],
            "confidence": 0.998,
            "span": {
                "offset": 452,
                "length": 5
            }
        },
        {
            "content": "umweltgerecht",
            "polygon": [
                5.6437,
                3.3534,
                6.4468,
                3.3527,
                6.4464,
                3.4976,
                5.6432,
                3.4994
            ],
            "confidence": 0.994,
            "span": {
                "offset": 458,
                "length": 13
            }
        },
        {
            "content": "entsorgen.",
            "polygon": [
                6.4824,
                3.3529,
                7.0727,
                3.3536,
                7.0727,
                3.5005,
                6.482,
                3.4976
            ],
            "confidence": 0.994,
            "span": {
                "offset": 472,
                "length": 10
            }
        },
        {
            "content": "VERKÄUFER",
            "polygon": [
                0.9703,
                4.3783,
                1.7611,
                4.3779,
                1.7611,
                4.506,
                0.9708,
                4.5039
            ],
            "confidence": 0.987,
            "span": {
                "offset": 483,
                "length": 9
            }
        },
        {
            "content": "P.O.",
            "polygon": [
                2.0177,
                4.3857,
                2.2679,
                4.384,
                2.2676,
                4.506,
                2.0178,
                4.506
            ],
            "confidence": 0.989,
            "span": {
                "offset": 493,
                "length": 4
            }
        },
        {
            "content": "NUMMER",
            "polygon": [
                2.3159,
                4.3844,
                2.8724,
                4.3833,
                2.8724,
                4.5053,
                2.3157,
                4.506
            ],
            "confidence": 0.998,
            "span": {
                "offset": 498,
                "length": 6
            }
        },
        {
            "content": "ANFORDERER",
            "polygon": [
                3.0816,
                4.3828,
                3.9702,
                4.3816,
                3.9698,
                4.5028,
                3.0816,
                4.5045
            ],
            "confidence": 0.994,
            "span": {
                "offset": 505,
                "length": 10
            }
        },
        {
            "content": "VERSANDWEG",
            "polygon": [
                4.1461,
                4.3786,
                5.0609,
                4.3784,
                5.0609,
                4.5046,
                4.1464,
                4.504
            ],
            "confidence": 0.995,
            "span": {
                "offset": 516,
                "length": 10
            }
        },
        {
            "content": "FREI",
            "polygon": [
                5.4105,
                4.242,
                5.6941,
                4.2433,
                5.6934,
                4.3673,
                5.4098,
                4.3659
            ],
            "confidence": 0.99,
            "span": {
                "offset": 527,
                "length": 4
            }
        },
        {
            "content": "(AN",
            "polygon": [
                5.7427,
                4.2435,
                5.9671,
                4.2429,
                5.9671,
                4.3656,
                5.7419,
                4.3669
            ],
            "confidence": 0.995,
            "span": {
                "offset": 532,
                "length": 3
            }
        },
        {
            "content": "BORD)-",
            "polygon": [
                5.4597,
                4.3792,
                5.9272,
                4.3825,
                5.9271,
                4.5058,
                5.4592,
                4.5033
            ],
            "confidence": 0.995,
            "span": {
                "offset": 536,
                "length": 6
            }
        },
        {
            "content": "PUNKT",
            "polygon": [
                5.4704,
                4.5166,
                5.9101,
                4.5178,
                5.9101,
                4.6389,
                5.4699,
                4.6394
            ],
            "confidence": 0.996,
            "span": {
                "offset": 543,
                "length": 5
            }
        },
        {
            "content": "BEDINGUNGEN",
            "polygon": [
                6.2891,
                4.3759,
                7.2323,
                4.3746,
                7.2323,
                4.4988,
                6.2891,
                4.4999
            ],
            "confidence": 0.993,
            "span": {
                "offset": 549,
                "length": 11
            }
        },
        {
            "content": "MusterTech",
            "polygon": [
                0.9847,
                4.8064,
                1.6927,
                4.8074,
                1.6927,
                4.9276,
                0.9848,
                4.9273
            ],
            "confidence": 0.996,
            "span": {
                "offset": 561,
                "length": 10
            }
        },
        {
            "content": "GmbH",
            "polygon": [
                0.9878,
                4.9605,
                1.3678,
                4.9611,
                1.3678,
                5.078,
                0.9877,
                5.0781
            ],
            "confidence": 0.988,
            "span": {
                "offset": 572,
                "length": 4
            }
        },
        {
            "content": "987654321",
            "polygon": [
                2.016,
                4.882,
                2.643,
                4.8822,
                2.6422,
                5.0032,
                2.0157,
                5.0019
            ],
            "confidence": 0.995,
            "span": {
                "offset": 577,
                "length": 9
            }
        },
        {
            "content": "Max",
            "polygon": [
                3.1427,
                4.8115,
                3.3967,
                4.8132,
                3.3967,
                4.9239,
                3.1421,
                4.9241
            ],
            "confidence": 0.997,
            "span": {
                "offset": 587,
                "length": 3
            }
        },
        {
            "content": "Mustermann",
            "polygon": [
                3.1418,
                4.9607,
                3.847,
                4.9649,
                3.847,
                5.0814,
                3.1418,
                5.0789
            ],
            "confidence": 0.994,
            "span": {
                "offset": 591,
                "length": 10
            }
        },
        {
            "content": "LHD",
            "polygon": [
                4.1733,
                4.8774,
                4.4236,
                4.8799,
                4.4226,
                5.0091,
                4.1728,
                5.0074
            ],
            "confidence": 0.997,
            "span": {
                "offset": 602,
                "length": 3
            }
        },
        {
            "content": "Express",
            "polygon": [
                4.4724,
                4.8804,
                4.9241,
                4.8827,
                4.9241,
                5.0121,
                4.4714,
                5.0092
            ],
            "confidence": 0.997,
            "span": {
                "offset": 606,
                "length": 7
            }
        },
        {
            "content": "Hafen",
            "polygon": [
                5.31,
                4.8036,
                5.6536,
                4.8025,
                5.6536,
                4.9197,
                5.3095,
                4.9204
            ],
            "confidence": 0.997,
            "span": {
                "offset": 614,
                "length": 5
            }
        },
        {
            "content": "Musterstadt",
            "polygon": [
                5.3074,
                4.9547,
                5.9842,
                4.9545,
                5.9842,
                5.0776,
                5.3078,
                5.079
            ],
            "confidence": 0.995,
            "span": {
                "offset": 620,
                "length": 11
            }
        },
        {
            "content": "Fällig",
            "polygon": [
                6.3466,
                4.7995,
                6.6397,
                4.7989,
                6.6395,
                4.9316,
                6.3464,
                4.933
            ],
            "confidence": 0.997,
            "span": {
                "offset": 632,
                "length": 6
            }
        },
        {
            "content": "bei",
            "polygon": [
                6.6878,
                4.7988,
                6.8619,
                4.7966,
                6.8619,
                4.9309,
                6.6877,
                4.9309
            ],
            "confidence": 0.997,
            "span": {
                "offset": 639,
                "length": 3
            }
        },
        {
            "content": "Erhalt",
            "polygon": [
                6.345,
                4.9525,
                6.6909,
                4.953,
                6.6909,
                5.0714,
                6.3449,
                5.0739
            ],
            "confidence": 0.995,
            "span": {
                "offset": 643,
                "length": 6
            }
        },
        {
            "content": "MENGE",
            "polygon": [
                1.2164,
                5.4206,
                1.6813,
                5.4207,
                1.6813,
                5.5371,
                1.2167,
                5.537
            ],
            "confidence": 0.997,
            "span": {
                "offset": 650,
                "length": 5
            }
        },
        {
            "content": "BESCHREIBUNG",
            "polygon": [
                3.2471,
                5.4174,
                4.2559,
                5.4168,
                4.2555,
                5.5371,
                3.2472,
                5.5371
            ],
            "confidence": 0.996,
            "span": {
                "offset": 656,
                "length": 12
            }
        },
        {
            "content": "EINZELPREIS",
            "polygon": [
                5.5582,
                5.413,
                6.382,
                5.4114,
                6.3818,
                5.532,
                5.5585,
                5.5346
            ],
            "confidence": 0.992,
            "span": {
                "offset": 669,
                "length": 11
            }
        },
        {
            "content": "SUMME",
            "polygon": [
                6.6621,
                5.4109,
                7.1354,
                5.4114,
                7.1354,
                5.5331,
                6.6622,
                5.5342
            ],
            "confidence": 0.998,
            "span": {
                "offset": 681,
                "length": 5
            }
        },
        {
            "content": "1",
            "polygon": [
                1.274,
                5.7597,
                1.4305,
                5.7582,
                1.4305,
                5.9556,
                1.2736,
                5.9567
            ],
            "confidence": 0.993,
            "span": {
                "offset": 687,
                "length": 1
            }
        },
        {
            "content": "Kopierer",
            "polygon": [
                2.6338,
                5.7314,
                3.5563,
                5.7272,
                3.5563,
                5.991,
                2.6342,
                5.9912
            ],
            "confidence": 0.916,
            "span": {
                "offset": 689,
                "length": 8
            }
        },
        {
            "content": "1500",
            "polygon": [
                5.5883,
                5.7894,
                6.0868,
                5.7881,
                6.0868,
                5.9677,
                5.5887,
                5.9701
            ],
            "confidence": 0.993,
            "span": {
                "offset": 698,
                "length": 4
            }
        },
        {
            "content": "1500",
            "polygon": [
                6.5611,
                5.7848,
                7.0727,
                5.7815,
                7.0727,
                5.9601,
                6.5615,
                5.9634
            ],
            "confidence": 0.989,
            "span": {
                "offset": 703,
                "length": 4
            }
        },
        {
            "content": "4",
            "polygon": [
                1.2226,
                6.211,
                1.3678,
                6.2065,
                1.3678,
                6.4141,
                1.2225,
                6.4144
            ],
            "confidence": 0.993,
            "span": {
                "offset": 708,
                "length": 1
            }
        },
        {
            "content": "Druckerpatronen",
            "polygon": [
                2.4521,
                6.1843,
                4.1889,
                6.164,
                4.1889,
                6.4283,
                2.4554,
                6.4543
            ],
            "confidence": 0.886,
            "span": {
                "offset": 710,
                "length": 15
            }
        },
        {
            "content": "30",
            "polygon": [
                5.6463,
                6.2242,
                5.9044,
                6.2263,
                5.9044,
                6.4294,
                5.646,
                6.4301
            ],
            "confidence": 0.999,
            "span": {
                "offset": 726,
                "length": 2
            }
        },
        {
            "content": "120",
            "polygon": [
                6.618,
                6.2132,
                7.0329,
                6.2104,
                7.0329,
                6.3816,
                6.6188,
                6.3824
            ],
            "confidence": 0.994,
            "span": {
                "offset": 729,
                "length": 3
            }
        },
        {
            "content": "2",
            "polygon": [
                1.203,
                6.6967,
                1.3621,
                6.6958,
                1.3621,
                6.9208,
                1.203,
                6.9193
            ],
            "confidence": 0.993,
            "span": {
                "offset": 733,
                "length": 1
            }
        },
        {
            "content": "Papierpaket",
            "polygon": [
                2.4847,
                6.637,
                3.7671,
                6.6126,
                3.7729,
                6.9042,
                2.4914,
                6.9214
            ],
            "confidence": 0.953,
            "span": {
                "offset": 735,
                "length": 11
            }
        },
        {
            "content": "10",
            "polygon": [
                5.6732,
                6.6768,
                5.9386,
                6.6767,
                5.9386,
                6.8587,
                5.6722,
                6.8587
            ],
            "confidence": 0.999,
            "span": {
                "offset": 747,
                "length": 2
            }
        },
        {
            "content": "20",
            "polygon": [
                6.6449,
                6.6773,
                6.9303,
                6.6769,
                6.9303,
                6.8587,
                6.6445,
                6.8587
            ],
            "confidence": 0.998,
            "span": {
                "offset": 750,
                "length": 2
            }
        },
        {
            "content": "ZWISCHENSUMME",
            "polygon": [
                5.2847,
                8.2397,
                6.423,
                8.2401,
                6.423,
                8.3642,
                5.2848,
                8.3636
            ],
            "confidence": 0.993,
            "span": {
                "offset": 753,
                "length": 13
            }
        },
        {
            "content": "1640",
            "polygon": [
                6.5469,
                8.2264,
                7.0158,
                8.2255,
                7.0158,
                8.4003,
                6.5466,
                8.3984
            ],
            "confidence": 0.927,
            "span": {
                "offset": 767,
                "length": 4
            }
        },
        {
            "content": "MEHRWERTSTEUER",
            "polygon": [
                5.1819,
                8.4976,
                6.4173,
                8.4957,
                6.4173,
                8.6206,
                5.1821,
                8.6211
            ],
            "confidence": 0.993,
            "span": {
                "offset": 772,
                "length": 14
            }
        },
        {
            "content": "$",
            "polygon": [
                6.5329,
                8.4697,
                6.72,
                8.471,
                6.72,
                8.6714,
                6.5331,
                8.6724
            ],
            "confidence": 0.142,
            "span": {
                "offset": 787,
                "length": 1
            }
        },
        {
            "content": "328",
            "polygon": [
                6.7823,
                8.472,
                7.1639,
                8.4753,
                7.1639,
                8.6756,
                6.7823,
                8.6724
            ],
            "confidence": 0.981,
            "span": {
                "offset": 789,
                "length": 3
            }
        },
        {
            "content": "VERPACKUNG",
            "polygon": [
                4.5973,
                8.7453,
                5.4709,
                8.7465,
                5.471,
                8.8752,
                4.5974,
                8.8753
            ],
            "confidence": 0.993,
            "span": {
                "offset": 793,
                "length": 10
            }
        },
        {
            "content": "UND",
            "polygon": [
                5.5199,
                8.7467,
                5.7734,
                8.7465,
                5.7736,
                8.8753,
                5.52,
                8.8749
            ],
            "confidence": 0.999,
            "span": {
                "offset": 804,
                "length": 3
            }
        },
        {
            "content": "VERSAND",
            "polygon": [
                5.8161,
                8.7464,
                6.4116,
                8.7454,
                6.4116,
                8.8749,
                5.8162,
                8.8753
            ],
            "confidence": 0.996,
            "span": {
                "offset": 808,
                "length": 7
            }
        },
        {
            "content": "0",
            "polygon": [
                6.7165,
                8.7652,
                6.8676,
                8.7622,
                6.8676,
                8.9323,
                6.7168,
                8.9323
            ],
            "confidence": 0.937,
            "span": {
                "offset": 816,
                "length": 1
            }
        },
        {
            "content": "SUMME",
            "polygon": [
                5.4881,
                9.0047,
                5.9446,
                9.004,
                5.9446,
                9.126,
                5.4884,
                9.126
            ],
            "confidence": 0.998,
            "span": {
                "offset": 818,
                "length": 5
            }
        },
        {
            "content": "FÄLLIG",
            "polygon": [
                5.9928,
                9.0044,
                6.4173,
                9.0024,
                6.4173,
                9.126,
                5.9929,
                9.1259
            ],
            "confidence": 0.665,
            "span": {
                "offset": 824,
                "length": 6
            }
        },
        {
            "content": "1968",
            "polygon": [
                6.5457,
                8.9906,
                7.0443,
                8.9872,
                7.0443,
                9.1999,
                6.5457,
                9.196
            ],
            "confidence": 0.975,
            "span": {
                "offset": 831,
                "length": 4
            }
        },
        {
            "content": "Alle",
            "polygon": [
                0.8335,
                9.3748,
                1.0498,
                9.3759,
                1.0491,
                9.5049,
                0.8329,
                9.5041
            ],
            "confidence": 0.99,
            "span": {
                "offset": 836,
                "length": 4
            }
        },
        {
            "content": "Schecks",
            "polygon": [
                1.0931,
                9.3757,
                1.5561,
                9.3747,
                1.5549,
                9.5052,
                1.0923,
                9.505
            ],
            "confidence": 0.997,
            "span": {
                "offset": 841,
                "length": 7
            }
        },
        {
            "content": "auszahlbar",
            "polygon": [
                1.5993,
                9.3746,
                2.2073,
                9.3741,
                2.206,
                9.5058,
                1.5982,
                9.5053
            ],
            "confidence": 0.994,
            "span": {
                "offset": 849,
                "length": 10
            }
        },
        {
            "content": "an",
            "polygon": [
                2.244,
                9.374,
                2.3717,
                9.3737,
                2.3704,
                9.5062,
                2.2428,
                9.5059
            ],
            "confidence": 0.998,
            "span": {
                "offset": 860,
                "length": 2
            }
        },
        {
            "content": "MusterTech",
            "polygon": [
                2.4214,
                9.3734,
                3.0661,
                9.372,
                3.0649,
                9.5058,
                2.4202,
                9.5063
            ],
            "confidence": 0.991,
            "span": {
                "offset": 863,
                "length": 10
            }
        },
        {
            "content": "GmbH",
            "polygon": [
                3.1137,
                9.372,
                3.4765,
                9.3703,
                3.4765,
                9.5041,
                3.1125,
                9.5058
            ],
            "confidence": 0.989,
            "span": {
                "offset": 874,
                "length": 4
            }
        },
        {
            "content": "Wenden",
            "polygon": [
                0.8314,
                9.6809,
                1.2954,
                9.6807,
                1.2952,
                9.8166,
                0.8311,
                9.8139
            ],
            "confidence": 0.998,
            "span": {
                "offset": 879,
                "length": 6
            }
        },
        {
            "content": "Sie",
            "polygon": [
                1.3454,
                9.6805,
                1.516,
                9.6801,
                1.5157,
                9.817,
                1.3452,
                9.8167
            ],
            "confidence": 0.999,
            "span": {
                "offset": 886,
                "length": 3
            }
        },
        {
            "content": "sich",
            "polygon": [
                1.5592,
                9.68,
                1.7731,
                9.6793,
                1.7726,
                9.8175,
                1.5589,
                9.8171
            ],
            "confidence": 0.992,
            "span": {
                "offset": 890,
                "length": 4
            }
        },
        {
            "content": "mit",
            "polygon": [
                1.8026,
                9.6792,
                1.9846,
                9.6791,
                1.9842,
                9.8178,
                1.8021,
                9.8175
            ],
            "confidence": 0.998,
            "span": {
                "offset": 895,
                "length": 3
            }
        },
        {
            "content": "Fragen",
            "polygon": [
                2.0255,
                9.6792,
                2.4054,
                9.6788,
                2.4051,
                9.8178,
                2.0251,
                9.8179
            ],
            "confidence": 0.998,
            "span": {
                "offset": 899,
                "length": 6
            }
        },
        {
            "content": "zu",
            "polygon": [
                2.4463,
                9.6787,
                2.5714,
                9.6785,
                2.5711,
                9.8176,
                2.446,
                9.8178
            ],
            "confidence": 0.996,
            "span": {
                "offset": 906,
                "length": 2
            }
        },
        {
            "content": "dieser",
            "polygon": [
                2.6169,
                9.6785,
                2.9558,
                9.6781,
                2.9558,
                9.8169,
                2.6166,
                9.8175
            ],
            "confidence": 0.996,
            "span": {
                "offset": 909,
                "length": 6
            }
        },
        {
            "content": "Rechnung",
            "polygon": [
                3.0013,
                9.678,
                3.5518,
                9.6772,
                3.5519,
                9.8168,
                3.0013,
                9.817
            ],
            "confidence": 0.994,
            "span": {
                "offset": 916,
                "length": 8
            }
        },
        {
            "content": "an",
            "polygon": [
                3.5996,
                9.6771,
                3.7269,
                9.6767,
                3.727,
                9.8171,
                3.5996,
                9.8169
            ],
            "confidence": 0.997,
            "span": {
                "offset": 925,
                "length": 2
            }
        },
        {
            "content": "Max",
            "polygon": [
                3.7747,
                9.6765,
                3.9999,
                9.676,
                3.9998,
                9.817,
                3.7747,
                9.8172
            ],
            "confidence": 0.993,
            "span": {
                "offset": 928,
                "length": 3
            }
        },
        {
            "content": "Mustermann,",
            "polygon": [
                4.0431,
                9.6759,
                4.7528,
                9.6738,
                4.7528,
                9.8138,
                4.043,
                9.8168
            ],
            "confidence": 0.992,
            "span": {
                "offset": 932,
                "length": 11
            }
        },
        {
            "content": "+4912345678,",
            "polygon": [
                4.8051,
                9.6733,
                5.608,
                9.6712,
                5.6078,
                9.8119,
                4.8051,
                9.8135
            ],
            "confidence": 0.992,
            "span": {
                "offset": 944,
                "length": 12
            }
        },
        {
            "content": "max.mustermann@mustertech.de",
            "polygon": [
                0.8325,
                9.8412,
                2.7299,
                9.831,
                2.7299,
                9.9601,
                0.833,
                9.9634
            ],
            "confidence": 0.963,
            "span": {
                "offset": 957,
                "length": 28
            }
        },
        {
            "content": "VIELEN",
            "polygon": [
                2.8804,
                10.5272,
                3.3286,
                10.5261,
                3.3284,
                10.6569,
                2.8806,
                10.6579
            ],
            "confidence": 0.995,
            "span": {
                "offset": 986,
                "length": 6
            }
        },
        {
            "content": "DANK",
            "polygon": [
                3.3805,
                10.5259,
                3.727,
                10.5231,
                3.7269,
                10.6565,
                3.3804,
                10.657
            ],
            "confidence": 0.992,
            "span": {
                "offset": 993,
                "length": 4
            }
        },
        {
            "content": "FÜR",
            "polygon": [
                3.7703,
                10.5229,
                4.0149,
                10.5225,
                4.0149,
                10.6554,
                3.7702,
                10.6564
            ],
            "confidence": 0.361,
            "span": {
                "offset": 998,
                "length": 3
            }
        },
        {
            "content": "IHRE",
            "polygon": [
                4.0582,
                10.5225,
                4.3419,
                10.5224,
                4.3418,
                10.6551,
                4.0582,
                10.6551
            ],
            "confidence": 0.989,
            "span": {
                "offset": 1002,
                "length": 4
            }
        },
        {
            "content": "BESTELLUNG!",
            "polygon": [
                4.3917,
                10.5227,
                5.2775,
                10.5212,
                5.2775,
                10.6544,
                4.3916,
                10.6548
            ],
            "confidence": 0.995,
            "span": {
                "offset": 1007,
                "length": 11
            }
        }
    ],
    "lines": [
        {
            "content": "MusterTech GmbH",
            "polygon": [
                0.9172,
                0.9837,
                2.3817,
                0.9829,
                2.3818,
                1.1362,
                0.9172,
                1.137
            ],
            "spans": [
                {
                    "offset": 0,
                    "length": 15
                }
            ]
        },
        {
            "content": "Ihre Technik - Unser Muster für Erfolg.",
            "polygon": [
                0.9195,
                1.1735,
                3.0715,
                1.175,
                3.0712,
                1.3081,
                0.9193,
                1.304
            ],
            "spans": [
                {
                    "offset": 16,
                    "length": 39
                }
            ]
        },
        {
            "content": "RECHNUNG",
            "polygon": [
                5.6838,
                0.9967,
                7.2404,
                0.9931,
                7.241,
                1.2304,
                5.6843,
                1.234
            ],
            "spans": [
                {
                    "offset": 56,
                    "length": 8
                }
            ]
        },
        {
            "content": "Musterstraße 123",
            "polygon": [
                0.9158,
                1.4895,
                1.9025,
                1.4902,
                1.9024,
                1.6129,
                0.9157,
                1.6121
            ],
            "spans": [
                {
                    "offset": 65,
                    "length": 16
                }
            ]
        },
        {
            "content": "12345 Musterstadt",
            "polygon": [
                0.9275,
                1.6422,
                1.9657,
                1.6458,
                1.9653,
                1.7644,
                0.9271,
                1.7608
            ],
            "spans": [
                {
                    "offset": 82,
                    "length": 17
                }
            ]
        },
        {
            "content": "+4912345678",
            "polygon": [
                0.9223,
                1.7969,
                1.6873,
                1.7973,
                1.6872,
                1.9129,
                0.9222,
                1.9125
            ],
            "spans": [
                {
                    "offset": 100,
                    "length": 11
                }
            ]
        },
        {
            "content": "RECHNUNGSNR. 123",
            "polygon": [
                5.9895,
                1.5714,
                7.2465,
                1.5693,
                7.2467,
                1.6945,
                5.9897,
                1.6965
            ],
            "spans": [
                {
                    "offset": 112,
                    "length": 16
                }
            ]
        },
        {
            "content": "DATUM: 16.10.2024",
            "polygon": [
                6.1045,
                1.7244,
                7.2507,
                1.7231,
                7.2509,
                1.8452,
                6.1047,
                1.8465
            ],
            "spans": [
                {
                    "offset": 129,
                    "length": 17
                }
            ]
        },
        {
            "content": "AN:",
            "polygon": [
                0.9156,
                2.0414,
                1.1387,
                2.0421,
                1.1383,
                2.1536,
                0.9152,
                2.1529
            ],
            "spans": [
                {
                    "offset": 147,
                    "length": 3
                }
            ]
        },
        {
            "content": "Herr Michael Buchhalter",
            "polygon": [
                0.9162,
                2.1906,
                2.2754,
                2.1906,
                2.2754,
                2.3142,
                0.9162,
                2.3142
            ],
            "spans": [
                {
                    "offset": 151,
                    "length": 23
                }
            ]
        },
        {
            "content": "Testlogistik AG",
            "polygon": [
                0.9145,
                2.3423,
                1.7654,
                2.3409,
                1.7656,
                2.4708,
                0.9147,
                2.4722
            ],
            "spans": [
                {
                    "offset": 175,
                    "length": 15
                }
            ]
        },
        {
            "content": "Testweg 456",
            "polygon": [
                0.9163,
                2.4958,
                1.6376,
                2.4959,
                1.6376,
                2.6224,
                0.9163,
                2.6223
            ],
            "spans": [
                {
                    "offset": 191,
                    "length": 11
                }
            ]
        },
        {
            "content": "67890 Testhausen",
            "polygon": [
                0.9145,
                2.6469,
                1.9527,
                2.6508,
                1.9522,
                2.7706,
                0.914,
                2.7667
            ],
            "spans": [
                {
                    "offset": 203,
                    "length": 16
                }
            ]
        },
        {
            "content": "+4987654321",
            "polygon": [
                0.9187,
                2.7977,
                1.6751,
                2.7986,
                1.675,
                2.9184,
                0.9186,
                2.9175
            ],
            "spans": [
                {
                    "offset": 220,
                    "length": 11
                }
            ]
        },
        {
            "content": "LIEFERADRESSE:",
            "polygon": [
                4.2525,
                2.0309,
                5.3396,
                2.0313,
                5.3395,
                2.1553,
                4.2525,
                2.1549
            ],
            "spans": [
                {
                    "offset": 232,
                    "length": 14
                }
            ]
        },
        {
            "content": "Frau Sabine Logistik",
            "polygon": [
                4.2529,
                2.186,
                5.4048,
                2.1883,
                5.4045,
                2.3135,
                4.2526,
                2.3112
            ],
            "spans": [
                {
                    "offset": 247,
                    "length": 20
                }
            ]
        },
        {
            "content": "Testlogistik AG",
            "polygon": [
                4.2517,
                2.3388,
                5.1023,
                2.3378,
                5.1024,
                2.4667,
                4.2518,
                2.4677
            ],
            "spans": [
                {
                    "offset": 268,
                    "length": 15
                }
            ]
        },
        {
            "content": "Teststraße 42",
            "polygon": [
                4.2533,
                2.4914,
                5.032,
                2.4928,
                5.0318,
                2.6118,
                4.2531,
                2.6104
            ],
            "spans": [
                {
                    "offset": 284,
                    "length": 13
                }
            ]
        },
        {
            "content": "09999 Testdorf",
            "polygon": [
                4.2522,
                2.6396,
                5.1125,
                2.641,
                5.1123,
                2.7629,
                4.252,
                2.7622
            ],
            "spans": [
                {
                    "offset": 298,
                    "length": 14
                }
            ]
        },
        {
            "content": "Telefon: +4987654322",
            "polygon": [
                4.2508,
                2.7925,
                5.512,
                2.7892,
                5.5123,
                2.915,
                4.2511,
                2.9167
            ],
            "spans": [
                {
                    "offset": 313,
                    "length": 20
                }
            ]
        },
        {
            "content": "KOMMENTARE ODER BESONDERE ANWEISUNGEN:",
            "polygon": [
                0.9163,
                3.2062,
                4.0397,
                3.2011,
                4.0399,
                3.3343,
                0.9165,
                3.3382
            ],
            "spans": [
                {
                    "offset": 334,
                    "length": 38
                }
            ]
        },
        {
            "content": "Bitte alle Geräte vor der Inbetriebnahme gründlich prüfen. Verpackungsmaterial bitte umweltgerecht entsorgen.",
            "polygon": [
                0.9176,
                3.3535,
                7.0694,
                3.3514,
                7.0695,
                3.498,
                0.9177,
                3.5001
            ],
            "spans": [
                {
                    "offset": 373,
                    "length": 109
                }
            ]
        },
        {
            "content": "VERKÄUFER",
            "polygon": [
                0.9703,
                4.375,
                1.7598,
                4.3777,
                1.7593,
                4.5057,
                0.9699,
                4.5031
            ],
            "spans": [
                {
                    "offset": 483,
                    "length": 9
                }
            ]
        },
        {
            "content": "P.O. NUMMER",
            "polygon": [
                2.0177,
                4.3831,
                2.8701,
                4.383,
                2.8701,
                4.5044,
                2.0177,
                4.5046
            ],
            "spans": [
                {
                    "offset": 493,
                    "length": 11
                }
            ]
        },
        {
            "content": "ANFORDERER",
            "polygon": [
                3.0816,
                4.3812,
                3.9677,
                4.3809,
                3.9678,
                4.5022,
                3.0816,
                4.5025
            ],
            "spans": [
                {
                    "offset": 505,
                    "length": 10
                }
            ]
        },
        {
            "content": "VERSANDWEG",
            "polygon": [
                4.1461,
                4.3774,
                5.0588,
                4.3783,
                5.0587,
                4.5031,
                4.146,
                4.5022
            ],
            "spans": [
                {
                    "offset": 516,
                    "length": 10
                }
            ]
        },
        {
            "content": "FREI (AN",
            "polygon": [
                5.41,
                4.2419,
                5.9636,
                4.243,
                5.9633,
                4.3659,
                5.4098,
                4.3648
            ],
            "spans": [
                {
                    "offset": 527,
                    "length": 8
                }
            ]
        },
        {
            "content": "BORD)-",
            "polygon": [
                5.4597,
                4.3788,
                5.9217,
                4.3813,
                5.9211,
                4.5037,
                5.459,
                4.5013
            ],
            "spans": [
                {
                    "offset": 536,
                    "length": 6
                }
            ]
        },
        {
            "content": "PUNKT",
            "polygon": [
                5.4698,
                4.5166,
                5.9097,
                4.5165,
                5.9097,
                4.6372,
                5.4699,
                4.6374
            ],
            "spans": [
                {
                    "offset": 543,
                    "length": 5
                }
            ]
        },
        {
            "content": "BEDINGUNGEN",
            "polygon": [
                6.289,
                4.3749,
                7.2273,
                4.3742,
                7.2274,
                4.4977,
                6.2891,
                4.4984
            ],
            "spans": [
                {
                    "offset": 549,
                    "length": 11
                }
            ]
        },
        {
            "content": "MusterTech",
            "polygon": [
                0.9847,
                4.8064,
                1.6922,
                4.8074,
                1.692,
                4.927,
                0.9845,
                4.926
            ],
            "spans": [
                {
                    "offset": 561,
                    "length": 10
                }
            ]
        },
        {
            "content": "GmbH",
            "polygon": [
                0.9878,
                4.9604,
                1.3663,
                4.9607,
                1.3662,
                5.077,
                0.9877,
                5.0768
            ],
            "spans": [
                {
                    "offset": 572,
                    "length": 4
                }
            ]
        },
        {
            "content": "987654321",
            "polygon": [
                2.016,
                4.8802,
                2.6403,
                4.8817,
                2.64,
                5.0023,
                2.0157,
                5.0007
            ],
            "spans": [
                {
                    "offset": 577,
                    "length": 9
                }
            ]
        },
        {
            "content": "Max",
            "polygon": [
                3.1427,
                4.8113,
                3.3929,
                4.813,
                3.3921,
                4.9248,
                3.1419,
                4.923
            ],
            "spans": [
                {
                    "offset": 587,
                    "length": 3
                }
            ]
        },
        {
            "content": "Mustermann",
            "polygon": [
                3.1418,
                4.9602,
                3.8464,
                4.9649,
                3.8456,
                5.0814,
                3.141,
                5.0772
            ],
            "spans": [
                {
                    "offset": 591,
                    "length": 10
                }
            ]
        },
        {
            "content": "LHD Express",
            "polygon": [
                4.1733,
                4.8774,
                4.9195,
                4.8825,
                4.9186,
                5.0114,
                4.1724,
                5.0062
            ],
            "spans": [
                {
                    "offset": 602,
                    "length": 11
                }
            ]
        },
        {
            "content": "Hafen",
            "polygon": [
                5.3092,
                4.8033,
                5.6503,
                4.8025,
                5.6506,
                4.9185,
                5.3095,
                4.9193
            ],
            "spans": [
                {
                    "offset": 614,
                    "length": 5
                }
            ]
        },
        {
            "content": "Musterstadt",
            "polygon": [
                5.3074,
                4.9542,
                5.9789,
                4.9539,
                5.979,
                5.0766,
                5.3075,
                5.0769
            ],
            "spans": [
                {
                    "offset": 620,
                    "length": 11
                }
            ]
        },
        {
            "content": "Fällig bei",
            "polygon": [
                6.3456,
                4.7995,
                6.8602,
                4.7965,
                6.861,
                4.9291,
                6.3464,
                4.9321
            ],
            "spans": [
                {
                    "offset": 632,
                    "length": 10
                }
            ]
        },
        {
            "content": "Erhalt",
            "polygon": [
                6.345,
                4.9525,
                6.6894,
                4.9531,
                6.6892,
                5.0731,
                6.3448,
                5.0726
            ],
            "spans": [
                {
                    "offset": 643,
                    "length": 6
                }
            ]
        },
        {
            "content": "MENGE",
            "polygon": [
                1.2164,
                5.4203,
                1.6794,
                5.4201,
                1.6794,
                5.5356,
                1.2164,
                5.5358
            ],
            "spans": [
                {
                    "offset": 650,
                    "length": 5
                }
            ]
        },
        {
            "content": "BESCHREIBUNG",
            "polygon": [
                3.2471,
                5.4164,
                4.2535,
                5.4159,
                4.2536,
                5.5363,
                3.2472,
                5.5367
            ],
            "spans": [
                {
                    "offset": 656,
                    "length": 12
                }
            ]
        },
        {
            "content": "EINZELPREIS",
            "polygon": [
                5.5582,
                5.413,
                6.3782,
                5.4112,
                6.3785,
                5.5314,
                5.5584,
                5.5333
            ],
            "spans": [
                {
                    "offset": 669,
                    "length": 11
                }
            ]
        },
        {
            "content": "SUMME",
            "polygon": [
                6.6621,
                5.4109,
                7.1349,
                5.4111,
                7.1349,
                5.5328,
                6.662,
                5.5327
            ],
            "spans": [
                {
                    "offset": 681,
                    "length": 5
                }
            ]
        },
        {
            "content": "1",
            "polygon": [
                1.274,
                5.7584,
                1.427,
                5.7587,
                1.4266,
                5.9538,
                1.2736,
                5.9535
            ],
            "spans": [
                {
                    "offset": 687,
                    "length": 1
                }
            ]
        },
        {
            "content": "Kopierer",
            "polygon": [
                2.6338,
                5.7249,
                3.5545,
                5.7236,
                3.5549,
                5.9887,
                2.6342,
                5.99
            ],
            "spans": [
                {
                    "offset": 689,
                    "length": 8
                }
            ]
        },
        {
            "content": "1500",
            "polygon": [
                5.5881,
                5.7894,
                6.0838,
                5.7878,
                6.0844,
                5.9656,
                5.5887,
                5.9672
            ],
            "spans": [
                {
                    "offset": 698,
                    "length": 4
                }
            ]
        },
        {
            "content": "1500",
            "polygon": [
                6.5604,
                5.7841,
                7.0677,
                5.7808,
                7.0689,
                5.9571,
                6.5615,
                5.9604
            ],
            "spans": [
                {
                    "offset": 703,
                    "length": 4
                }
            ]
        },
        {
            "content": "4",
            "polygon": [
                1.2226,
                6.2066,
                1.3664,
                6.2067,
                1.3663,
                6.4127,
                1.2225,
                6.4126
            ],
            "spans": [
                {
                    "offset": 708,
                    "length": 1
                }
            ]
        },
        {
            "content": "Druckerpatronen",
            "polygon": [
                2.4521,
                6.1843,
                4.1858,
                6.1641,
                4.1889,
                6.4339,
                2.4553,
                6.4541
            ],
            "spans": [
                {
                    "offset": 710,
                    "length": 15
                }
            ]
        },
        {
            "content": "30",
            "polygon": [
                5.6463,
                6.2241,
                5.9029,
                6.2245,
                5.9026,
                6.4273,
                5.646,
                6.4268
            ],
            "spans": [
                {
                    "offset": 726,
                    "length": 2
                }
            ]
        },
        {
            "content": "120",
            "polygon": [
                6.6178,
                6.2128,
                7.0268,
                6.2104,
                7.0278,
                6.38,
                6.6188,
                6.3824
            ],
            "spans": [
                {
                    "offset": 729,
                    "length": 3
                }
            ]
        },
        {
            "content": "2",
            "polygon": [
                1.2028,
                6.6955,
                1.3567,
                6.6954,
                1.3569,
                6.9179,
                1.203,
                6.918
            ],
            "spans": [
                {
                    "offset": 733,
                    "length": 1
                }
            ]
        },
        {
            "content": "Papierpaket",
            "polygon": [
                2.4846,
                6.6338,
                3.763,
                6.6112,
                3.7681,
                6.8993,
                2.4897,
                6.9214
            ],
            "spans": [
                {
                    "offset": 735,
                    "length": 11
                }
            ]
        },
        {
            "content": "10",
            "polygon": [
                5.6728,
                6.6759,
                5.9373,
                6.6769,
                5.9367,
                6.8586,
                5.6722,
                6.8577
            ],
            "spans": [
                {
                    "offset": 747,
                    "length": 2
                }
            ]
        },
        {
            "content": "20",
            "polygon": [
                6.6441,
                6.6761,
                6.9254,
                6.6755,
                6.9257,
                6.8566,
                6.6445,
                6.8572
            ],
            "spans": [
                {
                    "offset": 750,
                    "length": 2
                }
            ]
        },
        {
            "content": "ZWISCHENSUMME",
            "polygon": [
                5.2847,
                8.2388,
                6.4177,
                8.2399,
                6.4175,
                8.363,
                5.2846,
                8.3618
            ],
            "spans": [
                {
                    "offset": 753,
                    "length": 13
                }
            ]
        },
        {
            "content": "1640",
            "polygon": [
                6.5466,
                8.2247,
                7.0137,
                8.2246,
                7.0137,
                8.3974,
                6.5466,
                8.3975
            ],
            "spans": [
                {
                    "offset": 767,
                    "length": 4
                }
            ]
        },
        {
            "content": "MEHRWERTSTEUER",
            "polygon": [
                5.1819,
                8.4973,
                6.4158,
                8.4957,
                6.4159,
                8.6189,
                5.1821,
                8.6205
            ],
            "spans": [
                {
                    "offset": 772,
                    "length": 14
                }
            ]
        },
        {
            "content": "$ 328",
            "polygon": [
                6.5329,
                8.4696,
                7.1623,
                8.4723,
                7.1615,
                8.6717,
                6.5321,
                8.6691
            ],
            "spans": [
                {
                    "offset": 787,
                    "length": 5
                }
            ]
        },
        {
            "content": "VERPACKUNG UND VERSAND",
            "polygon": [
                4.5973,
                8.7451,
                6.4115,
                8.7448,
                6.4115,
                8.8747,
                4.5974,
                8.875
            ],
            "spans": [
                {
                    "offset": 793,
                    "length": 22
                }
            ]
        },
        {
            "content": "0",
            "polygon": [
                6.7165,
                8.7626,
                6.8626,
                8.7623,
                6.863,
                8.9306,
                6.7168,
                8.9309
            ],
            "spans": [
                {
                    "offset": 816,
                    "length": 1
                }
            ]
        },
        {
            "content": "SUMME FÄLLIG",
            "polygon": [
                5.4881,
                9.0047,
                6.4171,
                9.0022,
                6.4173,
                9.1244,
                5.4884,
                9.126
            ],
            "spans": [
                {
                    "offset": 818,
                    "length": 12
                }
            ]
        },
        {
            "content": "1968",
            "polygon": [
                6.5455,
                8.9866,
                7.0433,
                8.9862,
                7.0435,
                9.1954,
                6.5457,
                9.1958
            ],
            "spans": [
                {
                    "offset": 831,
                    "length": 4
                }
            ]
        },
        {
            "content": "Alle Schecks auszahlbar an MusterTech GmbH",
            "polygon": [
                0.8327,
                9.3749,
                3.473,
                9.3704,
                3.4732,
                9.5035,
                0.833,
                9.5077
            ],
            "spans": [
                {
                    "offset": 836,
                    "length": 42
                }
            ]
        },
        {
            "content": "Wenden Sie sich mit Fragen zu dieser Rechnung an Max Mustermann, +4912345678,",
            "polygon": [
                0.8309,
                9.6809,
                5.6054,
                9.6708,
                5.6057,
                9.8114,
                0.8312,
                9.821
            ],
            "spans": [
                {
                    "offset": 879,
                    "length": 77
                }
            ]
        },
        {
            "content": "max.mustermann@mustertech.de",
            "polygon": [
                0.8325,
                9.8379,
                2.7283,
                9.831,
                2.7288,
                9.9595,
                0.833,
                9.9634
            ],
            "spans": [
                {
                    "offset": 957,
                    "length": 28
                }
            ]
        },
        {
            "content": "VIELEN DANK FÜR IHRE BESTELLUNG!",
            "polygon": [
                2.8804,
                10.524,
                5.2733,
                10.5204,
                5.2735,
                10.6521,
                2.8806,
                10.6557
            ],
            "spans": [
                {
                    "offset": 986,
                    "length": 32
                }
            ]
        }
    ],
    "spans": [
        {
            "offset": 0,
            "length": 1018
        }
    ]
}